{
  "name": "Italian Serie B 2025/26",
  "matches": [
    {
      "round": "Matchday 1",
      "date": "2025-08-23",
      "team1": "US Catanzaro",
      "team2": "FC Südtirol",
      "score": {
      }
    },
    {
      "round": "Matchday 1",
      "date": "2025-08-23",
      "team1": "Empoli FC",
      "team2": "Calcio Padova",
      "score": {
      }
    },
    {
      "round": "Matchday 1",
      "date": "2025-08-23",
      "team1": "Virtus Entella",
      "team2": "Juve Stabia",
      "score": {
      }
    },
    {
      "round": "Matchday 1",
      "date": "2025-08-23",
      "team1": "Frosinone Calcio",
      "team2": "US Avellino",
      "score": {
      }
    },
    {
      "round": "Matchday 1",
      "date": "2025-08-23",
      "team1": "AC Monza",
      "team2": "Mantova 1911 SSD",
      "score": {
      }
    },
    {
      "round": "Matchday 1",
      "date": "2025-08-23",
      "team1": "Palermo FC",
      "team2": "AC Reggiana 1919",
      "score": {
      }
    },
    {
      "round": "Matchday 1",
      "date": "2025-08-23",
      "team1": "Delfino Pescara",
      "team2": "Cesena FC",
      "score": {
      }
    },
    {
      "round": "Matchday 1",
      "date": "2025-08-23",
      "team1": "Sampdoria",
      "team2": "Modena FC",
      "score": {
      }
    },
    {
      "round": "Matchday 1",
      "date": "2025-08-23",
      "team1": "Spezia Calcio",
      "team2": "Carrarese Calcio",
      "score": {
      }
    },
    {
      "round": "Matchday 1",
      "date": "2025-08-23",
      "team1": "Venezia FC",
      "team2": "SSC Bari",
      "score": {
      }
    },
    {
      "round": "Matchday 2",
      "date": "2025-08-30",
      "team1": "SSC Bari",
      "team2": "AC Monza",
      "score": {
      }
    },
    {
      "round": "Matchday 2",
      "date": "2025-08-30",
      "team1": "Carrarese Calcio",
      "team2": "Calcio Padova",
      "score": {
      }
    },
    {
      "round": "Matchday 2",
      "date": "2025-08-30",
      "team1": "Cesena FC",
      "team2": "Virtus Entella",
      "score": {
      }
    },
    {
      "round": "Matchday 2",
      "date": "2025-08-30",
      "team1": "Juve Stabia",
      "team2": "Venezia FC",
      "score": {
      }
    },
    {
      "round": "Matchday 2",
      "date": "2025-08-30",
      "team1": "Mantova 1911 SSD",
      "team2": "Delfino Pescara",
      "score": {
      }
    },
    {
      "round": "Matchday 2",
      "date": "2025-08-30",
      "team1": "Modena FC",
      "team2": "US Avellino",
      "score": {
      }
    },
    {
      "round": "Matchday 2",
      "date": "2025-08-30",
      "team1": "Palermo FC",
      "team2": "Frosinone Calcio",
      "score": {
      }
    },
    {
      "round": "Matchday 2",
      "date": "2025-08-30",
      "team1": "AC Reggiana 1919",
      "team2": "Empoli FC",
      "score": {
      }
    },
    {
      "round": "Matchday 2",
      "date": "2025-08-30",
      "team1": "Spezia Calcio",
      "team2": "US Catanzaro",
      "score": {
      }
    },
    {
      "round": "Matchday 2",
      "date": "2025-08-30",
      "team1": "FC Südtirol",
      "team2": "Sampdoria",
      "score": {
      }
    },
    {
      "round": "Matchday 3",
      "date": "2025-09-13",
      "team1": "US Avellino",
      "team2": "AC Monza",
      "score": {
      }
    },
    {
      "round": "Matchday 3",
      "date": "2025-09-13",
      "team1": "US Catanzaro",
      "team2": "Carrarese Calcio",
      "score": {
      }
    },
    {
      "round": "Matchday 3",
      "date": "2025-09-13",
      "team1": "Empoli FC",
      "team2": "Spezia Calcio",
      "score": {
      }
    },
    {
      "round": "Matchday 3",
      "date": "2025-09-13",
      "team1": "Virtus Entella",
      "team2": "Mantova 1911 SSD",
      "score": {
      }
    },
    {
      "round": "Matchday 3",
      "date": "2025-09-13",
      "team1": "Juve Stabia",
      "team2": "AC Reggiana 1919",
      "score": {
      }
    },
    {
      "round": "Matchday 3",
      "date": "2025-09-13",
      "team1": "Modena FC",
      "team2": "SSC Bari",
      "score": {
      }
    },
    {
      "round": "Matchday 3",
      "date": "2025-09-13",
      "team1": "Calcio Padova",
      "team2": "Frosinone Calcio",
      "score": {
      }
    },
    {
      "round": "Matchday 3",
      "date": "2025-09-13",
      "team1": "Delfino Pescara",
      "team2": "Venezia FC",
      "score": {
      }
    },
    {
      "round": "Matchday 3",
      "date": "2025-09-13",
      "team1": "Sampdoria",
      "team2": "Cesena FC",
      "score": {
      }
    },
    {
      "round": "Matchday 3",
      "date": "2025-09-13",
      "team1": "FC Südtirol",
      "team2": "Palermo FC",
      "score": {
      }
    },
    {
      "round": "Matchday 4",
      "date": "2025-09-20",
      "team1": "Carrarese Calcio",
      "team2": "US Avellino",
      "score": {
      }
    },
    {
      "round": "Matchday 4",
      "date": "2025-09-20",
      "team1": "Frosinone Calcio",
      "team2": "FC Südtirol",
      "score": {
      }
    },
    {
      "round": "Matchday 4",
      "date": "2025-09-20",
      "team1": "Mantova 1911 SSD",
      "team2": "Modena FC",
      "score": {
      }
    },
    {
      "round": "Matchday 4",
      "date": "2025-09-20",
      "team1": "AC Monza",
      "team2": "Sampdoria",
      "score": {
      }
    },
    {
      "round": "Matchday 4",
      "date": "2025-09-20",
      "team1": "Calcio Padova",
      "team2": "Virtus Entella",
      "score": {
      }
    },
    {
      "round": "Matchday 4",
      "date": "2025-09-20",
      "team1": "Palermo FC",
      "team2": "SSC Bari",
      "score": {
      }
    },
    {
      "round": "Matchday 4",
      "date": "2025-09-20",
      "team1": "Delfino Pescara",
      "team2": "Empoli FC",
      "score": {
      }
    },
    {
      "round": "Matchday 4",
      "date": "2025-09-20",
      "team1": "AC Reggiana 1919",
      "team2": "US Catanzaro",
      "score": {
      }
    },
    {
      "round": "Matchday 4",
      "date": "2025-09-20",
      "team1": "Spezia Calcio",
      "team2": "Juve Stabia",
      "score": {
      }
    },
    {
      "round": "Matchday 4",
      "date": "2025-09-20",
      "team1": "Venezia FC",
      "team2": "Cesena FC",
      "score": {
      }
    },
    {
      "round": "Matchday 5",
      "date": "2025-09-27",
      "team1": "US Avellino",
      "team2": "Virtus Entella",
      "score": {
      }
    },
    {
      "round": "Matchday 5",
      "date": "2025-09-27",
      "team1": "SSC Bari",
      "team2": "Sampdoria",
      "score": {
      }
    },
    {
      "round": "Matchday 5",
      "date": "2025-09-27",
      "team1": "US Catanzaro",
      "team2": "Juve Stabia",
      "score": {
      }
    },
    {
      "round": "Matchday 5",
      "date": "2025-09-27",
      "team1": "Cesena FC",
      "team2": "Palermo FC",
      "score": {
      }
    },
    {
      "round": "Matchday 5",
      "date": "2025-09-27",
      "team1": "Empoli FC",
      "team2": "Carrarese Calcio",
      "score": {
      }
    },
    {
      "round": "Matchday 5",
      "date": "2025-09-27",
      "team1": "Mantova 1911 SSD",
      "team2": "Frosinone Calcio",
      "score": {
      }
    },
    {
      "round": "Matchday 5",
      "date": "2025-09-27",
      "team1": "Modena FC",
      "team2": "Delfino Pescara",
      "score": {
      }
    },
    {
      "round": "Matchday 5",
      "date": "2025-09-27",
      "team1": "AC Monza",
      "team2": "Calcio Padova",
      "score": {
      }
    },
    {
      "round": "Matchday 5",
      "date": "2025-09-27",
      "team1": "FC Südtirol",
      "team2": "AC Reggiana 1919",
      "score": {
      }
    },
    {
      "round": "Matchday 5",
      "date": "2025-09-27",
      "team1": "Venezia FC",
      "team2": "Spezia Calcio",
      "score": {
      }
    },
    {
      "round": "Matchday 6",
      "date": "2025-09-30",
      "team1": "Carrarese Calcio",
      "team2": "Modena FC",
      "score": {
      }
    },
    {
      "round": "Matchday 6",
      "date": "2025-09-30",
      "team1": "Empoli FC",
      "team2": "AC Monza",
      "score": {
      }
    },
    {
      "round": "Matchday 6",
      "date": "2025-09-30",
      "team1": "Virtus Entella",
      "team2": "SSC Bari",
      "score": {
      }
    },
    {
      "round": "Matchday 6",
      "date": "2025-09-30",
      "team1": "Frosinone Calcio",
      "team2": "Cesena FC",
      "score": {
      }
    },
    {
      "round": "Matchday 6",
      "date": "2025-09-30",
      "team1": "Juve Stabia",
      "team2": "Mantova 1911 SSD",
      "score": {
      }
    },
    {
      "round": "Matchday 6",
      "date": "2025-09-30",
      "team1": "Calcio Padova",
      "team2": "US Avellino",
      "score": {
      }
    },
    {
      "round": "Matchday 6",
      "date": "2025-09-30",
      "team1": "Palermo FC",
      "team2": "Venezia FC",
      "score": {
      }
    },
    {
      "round": "Matchday 6",
      "date": "2025-09-30",
      "team1": "Delfino Pescara",
      "team2": "FC Südtirol",
      "score": {
      }
    },
    {
      "round": "Matchday 6",
      "date": "2025-09-30",
      "team1": "AC Reggiana 1919",
      "team2": "Spezia Calcio",
      "score": {
      }
    },
    {
      "round": "Matchday 6",
      "date": "2025-09-30",
      "team1": "Sampdoria",
      "team2": "US Catanzaro",
      "score": {
      }
    },
    {
      "round": "Matchday 7",
      "date": "2025-10-04",
      "team1": "US Avellino",
      "team2": "Mantova 1911 SSD",
      "score": {
      }
    },
    {
      "round": "Matchday 7",
      "date": "2025-10-04",
      "team1": "SSC Bari",
      "team2": "Calcio Padova",
      "score": {
      }
    },
    {
      "round": "Matchday 7",
      "date": "2025-10-04",
      "team1": "Carrarese Calcio",
      "team2": "Juve Stabia",
      "score": {
      }
    },
    {
      "round": "Matchday 7",
      "date": "2025-10-04",
      "team1": "Cesena FC",
      "team2": "AC Reggiana 1919",
      "score": {
      }
    },
    {
      "round": "Matchday 7",
      "date": "2025-10-04",
      "team1": "Modena FC",
      "team2": "Virtus Entella",
      "score": {
      }
    },
    {
      "round": "Matchday 7",
      "date": "2025-10-04",
      "team1": "AC Monza",
      "team2": "US Catanzaro",
      "score": {
      }
    },
    {
      "round": "Matchday 7",
      "date": "2025-10-04",
      "team1": "Sampdoria",
      "team2": "Delfino Pescara",
      "score": {
      }
    },
    {
      "round": "Matchday 7",
      "date": "2025-10-04",
      "team1": "Spezia Calcio",
      "team2": "Palermo FC",
      "score": {
      }
    },
    {
      "round": "Matchday 7",
      "date": "2025-10-04",
      "team1": "FC Südtirol",
      "team2": "Empoli FC",
      "score": {
      }
    },
    {
      "round": "Matchday 7",
      "date": "2025-10-04",
      "team1": "Venezia FC",
      "team2": "Frosinone Calcio",
      "score": {
      }
    },
    {
      "round": "Matchday 8",
      "date": "2025-10-18",
      "team1": "US Catanzaro",
      "team2": "Calcio Padova",
      "score": {
      }
    },
    {
      "round": "Matchday 8",
      "date": "2025-10-18",
      "team1": "Empoli FC",
      "team2": "Venezia FC",
      "score": {
      }
    },
    {
      "round": "Matchday 8",
      "date": "2025-10-18",
      "team1": "Virtus Entella",
      "team2": "Sampdoria",
      "score": {
      }
    },
    {
      "round": "Matchday 8",
      "date": "2025-10-18",
      "team1": "Frosinone Calcio",
      "team2": "AC Monza",
      "score": {
      }
    },
    {
      "round": "Matchday 8",
      "date": "2025-10-18",
      "team1": "Juve Stabia",
      "team2": "US Avellino",
      "score": {
      }
    },
    {
      "round": "Matchday 8",
      "date": "2025-10-18",
      "team1": "Mantova 1911 SSD",
      "team2": "FC Südtirol",
      "score": {
      }
    },
    {
      "round": "Matchday 8",
      "date": "2025-10-18",
      "team1": "Palermo FC",
      "team2": "Modena FC",
      "score": {
      }
    },
    {
      "round": "Matchday 8",
      "date": "2025-10-18",
      "team1": "Delfino Pescara",
      "team2": "Carrarese Calcio",
      "score": {
      }
    },
    {
      "round": "Matchday 8",
      "date": "2025-10-18",
      "team1": "AC Reggiana 1919",
      "team2": "SSC Bari",
      "score": {
      }
    },
    {
      "round": "Matchday 8",
      "date": "2025-10-18",
      "team1": "Spezia Calcio",
      "team2": "Cesena FC",
      "score": {
      }
    },
    {
      "round": "Matchday 9",
      "date": "2025-10-25",
      "team1": "US Avellino",
      "team2": "Spezia Calcio",
      "score": {
      }
    },
    {
      "round": "Matchday 9",
      "date": "2025-10-25",
      "team1": "SSC Bari",
      "team2": "Mantova 1911 SSD",
      "score": {
      }
    },
    {
      "round": "Matchday 9",
      "date": "2025-10-25",
      "team1": "Carrarese Calcio",
      "team2": "Venezia FC",
      "score": {
      }
    },
    {
      "round": "Matchday 9",
      "date": "2025-10-25",
      "team1": "US Catanzaro",
      "team2": "Palermo FC",
      "score": {
      }
    },
    {
      "round": "Matchday 9",
      "date": "2025-10-25",
      "team1": "Virtus Entella",
      "team2": "Delfino Pescara",
      "score": {
      }
    },
    {
      "round": "Matchday 9",
      "date": "2025-10-25",
      "team1": "Modena FC",
      "team2": "Empoli FC",
      "score": {
      }
    },
    {
      "round": "Matchday 9",
      "date": "2025-10-25",
      "team1": "AC Monza",
      "team2": "AC Reggiana 1919",
      "score": {
      }
    },
    {
      "round": "Matchday 9",
      "date": "2025-10-25",
      "team1": "Calcio Padova",
      "team2": "Juve Stabia",
      "score": {
      }
    },
    {
      "round": "Matchday 9",
      "date": "2025-10-25",
      "team1": "Sampdoria",
      "team2": "Frosinone Calcio",
      "score": {
      }
    },
    {
      "round": "Matchday 9",
      "date": "2025-10-25",
      "team1": "FC Südtirol",
      "team2": "Cesena FC",
      "score": {
      }
    },
    {
      "round": "Matchday 10",
      "date": "2025-10-28",
      "team1": "Cesena FC",
      "team2": "Carrarese Calcio",
      "score": {
      }
    },
    {
      "round": "Matchday 10",
      "date": "2025-10-28",
      "team1": "Empoli FC",
      "team2": "Sampdoria",
      "score": {
      }
    },
    {
      "round": "Matchday 10",
      "date": "2025-10-28",
      "team1": "Frosinone Calcio",
      "team2": "Virtus Entella",
      "score": {
      }
    },
    {
      "round": "Matchday 10",
      "date": "2025-10-28",
      "team1": "Juve Stabia",
      "team2": "SSC Bari",
      "score": {
      }
    },
    {
      "round": "Matchday 10",
      "date": "2025-10-28",
      "team1": "Mantova 1911 SSD",
      "team2": "US Catanzaro",
      "score": {
      }
    },
    {
      "round": "Matchday 10",
      "date": "2025-10-28",
      "team1": "Palermo FC",
      "team2": "AC Monza",
      "score": {
      }
    },
    {
      "round": "Matchday 10",
      "date": "2025-10-28",
      "team1": "Delfino Pescara",
      "team2": "US Avellino",
      "score": {
      }
    },
    {
      "round": "Matchday 10",
      "date": "2025-10-28",
      "team1": "AC Reggiana 1919",
      "team2": "Modena FC",
      "score": {
      }
    },
    {
      "round": "Matchday 10",
      "date": "2025-10-28",
      "team1": "Spezia Calcio",
      "team2": "Calcio Padova",
      "score": {
      }
    },
    {
      "round": "Matchday 10",
      "date": "2025-10-28",
      "team1": "Venezia FC",
      "team2": "FC Südtirol",
      "score": {
      }
    },
    {
      "round": "Matchday 11",
      "date": "2025-11-01",
      "team1": "US Avellino",
      "team2": "AC Reggiana 1919",
      "score": {
      }
    },
    {
      "round": "Matchday 11",
      "date": "2025-11-01",
      "team1": "SSC Bari",
      "team2": "Cesena FC",
      "score": {
      }
    },
    {
      "round": "Matchday 11",
      "date": "2025-11-01",
      "team1": "Carrarese Calcio",
      "team2": "Frosinone Calcio",
      "score": {
      }
    },
    {
      "round": "Matchday 11",
      "date": "2025-11-01",
      "team1": "US Catanzaro",
      "team2": "Venezia FC",
      "score": {
      }
    },
    {
      "round": "Matchday 11",
      "date": "2025-11-01",
      "team1": "Virtus Entella",
      "team2": "Empoli FC",
      "score": {
      }
    },
    {
      "round": "Matchday 11",
      "date": "2025-11-01",
      "team1": "Modena FC",
      "team2": "Juve Stabia",
      "score": {
      }
    },
    {
      "round": "Matchday 11",
      "date": "2025-11-01",
      "team1": "AC Monza",
      "team2": "Spezia Calcio",
      "score": {
      }
    },
    {
      "round": "Matchday 11",
      "date": "2025-11-01",
      "team1": "Calcio Padova",
      "team2": "FC Südtirol",
      "score": {
      }
    },
    {
      "round": "Matchday 11",
      "date": "2025-11-01",
      "team1": "Palermo FC",
      "team2": "Delfino Pescara",
      "score": {
      }
    },
    {
      "round": "Matchday 11",
      "date": "2025-11-01",
      "team1": "Sampdoria",
      "team2": "Mantova 1911 SSD",
      "score": {
      }
    },
    {
      "round": "Matchday 12",
      "date": "2025-11-08",
      "team1": "Cesena FC",
      "team2": "US Avellino",
      "score": {
      }
    },
    {
      "round": "Matchday 12",
      "date": "2025-11-08",
      "team1": "Empoli FC",
      "team2": "US Catanzaro",
      "score": {
      }
    },
    {
      "round": "Matchday 12",
      "date": "2025-11-08",
      "team1": "Frosinone Calcio",
      "team2": "Modena FC",
      "score": {
      }
    },
    {
      "round": "Matchday 12",
      "date": "2025-11-08",
      "team1": "Juve Stabia",
      "team2": "Palermo FC",
      "score": {
      }
    },
    {
      "round": "Matchday 12",
      "date": "2025-11-08",
      "team1": "Mantova 1911 SSD",
      "team2": "Calcio Padova",
      "score": {
      }
    },
    {
      "round": "Matchday 12",
      "date": "2025-11-08",
      "team1": "Delfino Pescara",
      "team2": "AC Monza",
      "score": {
      }
    },
    {
      "round": "Matchday 12",
      "date": "2025-11-08",
      "team1": "AC Reggiana 1919",
      "team2": "Virtus Entella",
      "score": {
      }
    },
    {
      "round": "Matchday 12",
      "date": "2025-11-08",
      "team1": "Spezia Calcio",
      "team2": "SSC Bari",
      "score": {
      }
    },
    {
      "round": "Matchday 12",
      "date": "2025-11-08",
      "team1": "FC Südtirol",
      "team2": "Carrarese Calcio",
      "score": {
      }
    },
    {
      "round": "Matchday 12",
      "date": "2025-11-08",
      "team1": "Venezia FC",
      "team2": "Sampdoria",
      "score": {
      }
    },
    {
      "round": "Matchday 13",
      "date": "2025-11-22",
      "team1": "US Avellino",
      "team2": "Empoli FC",
      "score": {
      }
    },
    {
      "round": "Matchday 13",
      "date": "2025-11-22",
      "team1": "SSC Bari",
      "team2": "Frosinone Calcio",
      "score": {
      }
    },
    {
      "round": "Matchday 13",
      "date": "2025-11-22",
      "team1": "Carrarese Calcio",
      "team2": "AC Reggiana 1919",
      "score": {
      }
    },
    {
      "round": "Matchday 13",
      "date": "2025-11-22",
      "team1": "US Catanzaro",
      "team2": "Delfino Pescara",
      "score": {
      }
    },
    {
      "round": "Matchday 13",
      "date": "2025-11-22",
      "team1": "Virtus Entella",
      "team2": "Palermo FC",
      "score": {
      }
    },
    {
      "round": "Matchday 13",
      "date": "2025-11-22",
      "team1": "Mantova 1911 SSD",
      "team2": "Spezia Calcio",
      "score": {
      }
    },
    {
      "round": "Matchday 13",
      "date": "2025-11-22",
      "team1": "Modena FC",
      "team2": "FC Südtirol",
      "score": {
      }
    },
    {
      "round": "Matchday 13",
      "date": "2025-11-22",
      "team1": "AC Monza",
      "team2": "Cesena FC",
      "score": {
      }
    },
    {
      "round": "Matchday 13",
      "date": "2025-11-22",
      "team1": "Calcio Padova",
      "team2": "Venezia FC",
      "score": {
      }
    },
    {
      "round": "Matchday 13",
      "date": "2025-11-22",
      "team1": "Sampdoria",
      "team2": "Juve Stabia",
      "score": {
      }
    },
    {
      "round": "Matchday 14",
      "date": "2025-11-29",
      "team1": "US Catanzaro",
      "team2": "Virtus Entella",
      "score": {
      }
    },
    {
      "round": "Matchday 14",
      "date": "2025-11-29",
      "team1": "Cesena FC",
      "team2": "Modena FC",
      "score": {
      }
    },
    {
      "round": "Matchday 14",
      "date": "2025-11-29",
      "team1": "Empoli FC",
      "team2": "SSC Bari",
      "score": {
      }
    },
    {
      "round": "Matchday 14",
      "date": "2025-11-29",
      "team1": "Juve Stabia",
      "team2": "AC Monza",
      "score": {
      }
    },
    {
      "round": "Matchday 14",
      "date": "2025-11-29",
      "team1": "Palermo FC",
      "team2": "Carrarese Calcio",
      "score": {
      }
    },
    {
      "round": "Matchday 14",
      "date": "2025-11-29",
      "team1": "Delfino Pescara",
      "team2": "Calcio Padova",
      "score": {
      }
    },
    {
      "round": "Matchday 14",
      "date": "2025-11-29",
      "team1": "AC Reggiana 1919",
      "team2": "Frosinone Calcio",
      "score": {
      }
    },
    {
      "round": "Matchday 14",
      "date": "2025-11-29",
      "team1": "Spezia Calcio",
      "team2": "Sampdoria",
      "score": {
      }
    },
    {
      "round": "Matchday 14",
      "date": "2025-11-29",
      "team1": "FC Südtirol",
      "team2": "US Avellino",
      "score": {
      }
    },
    {
      "round": "Matchday 14",
      "date": "2025-11-29",
      "team1": "Venezia FC",
      "team2": "Mantova 1911 SSD",
      "score": {
      }
    },
    {
      "round": "Matchday 15",
      "date": "2025-12-08",
      "team1": "US Avellino",
      "team2": "Venezia FC",
      "score": {
      }
    },
    {
      "round": "Matchday 15",
      "date": "2025-12-08",
      "team1": "SSC Bari",
      "team2": "Delfino Pescara",
      "score": {
      }
    },
    {
      "round": "Matchday 15",
      "date": "2025-12-08",
      "team1": "Empoli FC",
      "team2": "Palermo FC",
      "score": {
      }
    },
    {
      "round": "Matchday 15",
      "date": "2025-12-08",
      "team1": "Virtus Entella",
      "team2": "Spezia Calcio",
      "score": {
      }
    },
    {
      "round": "Matchday 15",
      "date": "2025-12-08",
      "team1": "Frosinone Calcio",
      "team2": "Juve Stabia",
      "score": {
      }
    },
    {
      "round": "Matchday 15",
      "date": "2025-12-08",
      "team1": "Mantova 1911 SSD",
      "team2": "AC Reggiana 1919",
      "score": {
      }
    },
    {
      "round": "Matchday 15",
      "date": "2025-12-08",
      "team1": "Modena FC",
      "team2": "US Catanzaro",
      "score": {
      }
    },
    {
      "round": "Matchday 15",
      "date": "2025-12-08",
      "team1": "AC Monza",
      "team2": "FC Südtirol",
      "score": {
      }
    },
    {
      "round": "Matchday 15",
      "date": "2025-12-08",
      "team1": "Calcio Padova",
      "team2": "Cesena FC",
      "score": {
      }
    },
    {
      "round": "Matchday 15",
      "date": "2025-12-08",
      "team1": "Sampdoria",
      "team2": "Carrarese Calcio",
      "score": {
      }
    },
    {
      "round": "Matchday 16",
      "date": "2025-12-13",
      "team1": "Carrarese Calcio",
      "team2": "Virtus Entella",
      "score": {
      }
    },
    {
      "round": "Matchday 16",
      "date": "2025-12-13",
      "team1": "US Catanzaro",
      "team2": "US Avellino",
      "score": {
      }
    },
    {
      "round": "Matchday 16",
      "date": "2025-12-13",
      "team1": "Cesena FC",
      "team2": "Mantova 1911 SSD",
      "score": {
      }
    },
    {
      "round": "Matchday 16",
      "date": "2025-12-13",
      "team1": "Juve Stabia",
      "team2": "Empoli FC",
      "score": {
      }
    },
    {
      "round": "Matchday 16",
      "date": "2025-12-13",
      "team1": "Palermo FC",
      "team2": "Sampdoria",
      "score": {
      }
    },
    {
      "round": "Matchday 16",
      "date": "2025-12-13",
      "team1": "Delfino Pescara",
      "team2": "Frosinone Calcio",
      "score": {
      }
    },
    {
      "round": "Matchday 16",
      "date": "2025-12-13",
      "team1": "AC Reggiana 1919",
      "team2": "Calcio Padova",
      "score": {
      }
    },
    {
      "round": "Matchday 16",
      "date": "2025-12-13",
      "team1": "Spezia Calcio",
      "team2": "Modena FC",
      "score": {
      }
    },
    {
      "round": "Matchday 16",
      "date": "2025-12-13",
      "team1": "FC Südtirol",
      "team2": "SSC Bari",
      "score": {
      }
    },
    {
      "round": "Matchday 16",
      "date": "2025-12-13",
      "team1": "Venezia FC",
      "team2": "AC Monza",
      "score": {
      }
    },
    {
      "round": "Matchday 17",
      "date": "2025-12-20",
      "team1": "US Avellino",
      "team2": "Palermo FC",
      "score": {
      }
    },
    {
      "round": "Matchday 17",
      "date": "2025-12-20",
      "team1": "SSC Bari",
      "team2": "US Catanzaro",
      "score": {
      }
    },
    {
      "round": "Matchday 17",
      "date": "2025-12-20",
      "team1": "Cesena FC",
      "team2": "Juve Stabia",
      "score": {
      }
    },
    {
      "round": "Matchday 17",
      "date": "2025-12-20",
      "team1": "Virtus Entella",
      "team2": "FC Südtirol",
      "score": {
      }
    },
    {
      "round": "Matchday 17",
      "date": "2025-12-20",
      "team1": "Frosinone Calcio",
      "team2": "Spezia Calcio",
      "score": {
      }
    },
    {
      "round": "Matchday 17",
      "date": "2025-12-20",
      "team1": "Mantova 1911 SSD",
      "team2": "Empoli FC",
      "score": {
      }
    },
    {
      "round": "Matchday 17",
      "date": "2025-12-20",
      "team1": "Modena FC",
      "team2": "Venezia FC",
      "score": {
      }
    },
    {
      "round": "Matchday 17",
      "date": "2025-12-20",
      "team1": "AC Monza",
      "team2": "Carrarese Calcio",
      "score": {
      }
    },
    {
      "round": "Matchday 17",
      "date": "2025-12-20",
      "team1": "Calcio Padova",
      "team2": "Sampdoria",
      "score": {
      }
    },
    {
      "round": "Matchday 17",
      "date": "2025-12-20",
      "team1": "Delfino Pescara",
      "team2": "AC Reggiana 1919",
      "score": {
      }
    },
    {
      "round": "Matchday 18",
      "date": "2025-12-27",
      "team1": "SSC Bari",
      "team2": "US Avellino",
      "score": {
      }
    },
    {
      "round": "Matchday 18",
      "date": "2025-12-27",
      "team1": "Carrarese Calcio",
      "team2": "Mantova 1911 SSD",
      "score": {
      }
    },
    {
      "round": "Matchday 18",
      "date": "2025-12-27",
      "team1": "US Catanzaro",
      "team2": "Cesena FC",
      "score": {
      }
    },
    {
      "round": "Matchday 18",
      "date": "2025-12-27",
      "team1": "Empoli FC",
      "team2": "Frosinone Calcio",
      "score": {
      }
    },
    {
      "round": "Matchday 18",
      "date": "2025-12-27",
      "team1": "Juve Stabia",
      "team2": "FC Südtirol",
      "score": {
      }
    },
    {
      "round": "Matchday 18",
      "date": "2025-12-27",
      "team1": "Modena FC",
      "team2": "AC Monza",
      "score": {
      }
    },
    {
      "round": "Matchday 18",
      "date": "2025-12-27",
      "team1": "Palermo FC",
      "team2": "Calcio Padova",
      "score": {
      }
    },
    {
      "round": "Matchday 18",
      "date": "2025-12-27",
      "team1": "Sampdoria",
      "team2": "AC Reggiana 1919",
      "score": {
      }
    },
    {
      "round": "Matchday 18",
      "date": "2025-12-27",
      "team1": "Spezia Calcio",
      "team2": "Delfino Pescara",
      "score": {
      }
    },
    {
      "round": "Matchday 18",
      "date": "2025-12-27",
      "team1": "Venezia FC",
      "team2": "Virtus Entella",
      "score": {
      }
    },
    {
      "round": "Matchday 19",
      "date": "2026-01-10",
      "team1": "US Avellino",
      "team2": "Sampdoria",
      "score": {
      }
    },
    {
      "round": "Matchday 19",
      "date": "2026-01-10",
      "team1": "Carrarese Calcio",
      "team2": "SSC Bari",
      "score": {
      }
    },
    {
      "round": "Matchday 19",
      "date": "2026-01-10",
      "team1": "Cesena FC",
      "team2": "Empoli FC",
      "score": {
      }
    },
    {
      "round": "Matchday 19",
      "date": "2026-01-10",
      "team1": "Virtus Entella",
      "team2": "AC Monza",
      "score": {
      }
    },
    {
      "round": "Matchday 19",
      "date": "2026-01-10",
      "team1": "Frosinone Calcio",
      "team2": "US Catanzaro",
      "score": {
      }
    },
    {
      "round": "Matchday 19",
      "date": "2026-01-10",
      "team1": "Juve Stabia",
      "team2": "Delfino Pescara",
      "score": {
      }
    },
    {
      "round": "Matchday 19",
      "date": "2026-01-10",
      "team1": "Mantova 1911 SSD",
      "team2": "Palermo FC",
      "score": {
      }
    },
    {
      "round": "Matchday 19",
      "date": "2026-01-10",
      "team1": "Calcio Padova",
      "team2": "Modena FC",
      "score": {
      }
    },
    {
      "round": "Matchday 19",
      "date": "2026-01-10",
      "team1": "AC Reggiana 1919",
      "team2": "Venezia FC",
      "score": {
      }
    },
    {
      "round": "Matchday 19",
      "date": "2026-01-10",
      "team1": "FC Südtirol",
      "team2": "Spezia Calcio",
      "score": {
      }
    },
    {
      "round": "Matchday 20",
      "date": "2026-01-17",
      "team1": "US Avellino",
      "team2": "Carrarese Calcio",
      "score": {
      }
    },
    {
      "round": "Matchday 20",
      "date": "2026-01-17",
      "team1": "SSC Bari",
      "team2": "Juve Stabia",
      "score": {
      }
    },
    {
      "round": "Matchday 20",
      "date": "2026-01-17",
      "team1": "Empoli FC",
      "team2": "FC Südtirol",
      "score": {
      }
    },
    {
      "round": "Matchday 20",
      "date": "2026-01-17",
      "team1": "AC Monza",
      "team2": "Frosinone Calcio",
      "score": {
      }
    },
    {
      "round": "Matchday 20",
      "date": "2026-01-17",
      "team1": "Calcio Padova",
      "team2": "Mantova 1911 SSD",
      "score": {
      }
    },
    {
      "round": "Matchday 20",
      "date": "2026-01-17",
      "team1": "Palermo FC",
      "team2": "Spezia Calcio",
      "score": {
      }
    },
    {
      "round": "Matchday 20",
      "date": "2026-01-17",
      "team1": "Delfino Pescara",
      "team2": "Modena FC",
      "score": {
      }
    },
    {
      "round": "Matchday 20",
      "date": "2026-01-17",
      "team1": "AC Reggiana 1919",
      "team2": "Cesena FC",
      "score": {
      }
    },
    {
      "round": "Matchday 20",
      "date": "2026-01-17",
      "team1": "Sampdoria",
      "team2": "Virtus Entella",
      "score": {
      }
    },
    {
      "round": "Matchday 20",
      "date": "2026-01-17",
      "team1": "Venezia FC",
      "team2": "US Catanzaro",
      "score": {
      }
    },
    {
      "round": "Matchday 21",
      "date": "2026-01-24",
      "team1": "Carrarese Calcio",
      "team2": "Empoli FC",
      "score": {
      }
    },
    {
      "round": "Matchday 21",
      "date": "2026-01-24",
      "team1": "US Catanzaro",
      "team2": "Sampdoria",
      "score": {
      }
    },
    {
      "round": "Matchday 21",
      "date": "2026-01-24",
      "team1": "Cesena FC",
      "team2": "SSC Bari",
      "score": {
      }
    },
    {
      "round": "Matchday 21",
      "date": "2026-01-24",
      "team1": "Frosinone Calcio",
      "team2": "AC Reggiana 1919",
      "score": {
      }
    },
    {
      "round": "Matchday 21",
      "date": "2026-01-24",
      "team1": "Juve Stabia",
      "team2": "Virtus Entella",
      "score": {
      }
    },
    {
      "round": "Matchday 21",
      "date": "2026-01-24",
      "team1": "Mantova 1911 SSD",
      "team2": "Venezia FC",
      "score": {
      }
    },
    {
      "round": "Matchday 21",
      "date": "2026-01-24",
      "team1": "Modena FC",
      "team2": "Palermo FC",
      "score": {
      }
    },
    {
      "round": "Matchday 21",
      "date": "2026-01-24",
      "team1": "AC Monza",
      "team2": "Delfino Pescara",
      "score": {
      }
    },
    {
      "round": "Matchday 21",
      "date": "2026-01-24",
      "team1": "Spezia Calcio",
      "team2": "US Avellino",
      "score": {
      }
    },
    {
      "round": "Matchday 21",
      "date": "2026-01-24",
      "team1": "FC Südtirol",
      "team2": "Calcio Padova",
      "score": {
      }
    },
    {
      "round": "Matchday 22",
      "date": "2026-01-31",
      "team1": "US Avellino",
      "team2": "Cesena FC",
      "score": {
      }
    },
    {
      "round": "Matchday 22",
      "date": "2026-01-31",
      "team1": "SSC Bari",
      "team2": "Palermo FC",
      "score": {
      }
    },
    {
      "round": "Matchday 22",
      "date": "2026-01-31",
      "team1": "Empoli FC",
      "team2": "Modena FC",
      "score": {
      }
    },
    {
      "round": "Matchday 22",
      "date": "2026-01-31",
      "team1": "Virtus Entella",
      "team2": "Frosinone Calcio",
      "score": {
      }
    },
    {
      "round": "Matchday 22",
      "date": "2026-01-31",
      "team1": "Calcio Padova",
      "team2": "AC Monza",
      "score": {
      }
    },
    {
      "round": "Matchday 22",
      "date": "2026-01-31",
      "team1": "Delfino Pescara",
      "team2": "Mantova 1911 SSD",
      "score": {
      }
    },
    {
      "round": "Matchday 22",
      "date": "2026-01-31",
      "team1": "AC Reggiana 1919",
      "team2": "Juve Stabia",
      "score": {
      }
    },
    {
      "round": "Matchday 22",
      "date": "2026-01-31",
      "team1": "Sampdoria",
      "team2": "Spezia Calcio",
      "score": {
      }
    },
    {
      "round": "Matchday 22",
      "date": "2026-01-31",
      "team1": "FC Südtirol",
      "team2": "US Catanzaro",
      "score": {
      }
    },
    {
      "round": "Matchday 22",
      "date": "2026-01-31",
      "team1": "Venezia FC",
      "team2": "Carrarese Calcio",
      "score": {
      }
    },
    {
      "round": "Matchday 23",
      "date": "2026-02-07",
      "team1": "Carrarese Calcio",
      "team2": "FC Südtirol",
      "score": {
      }
    },
    {
      "round": "Matchday 23",
      "date": "2026-02-07",
      "team1": "US Catanzaro",
      "team2": "AC Reggiana 1919",
      "score": {
      }
    },
    {
      "round": "Matchday 23",
      "date": "2026-02-07",
      "team1": "Cesena FC",
      "team2": "Delfino Pescara",
      "score": {
      }
    },
    {
      "round": "Matchday 23",
      "date": "2026-02-07",
      "team1": "Frosinone Calcio",
      "team2": "Venezia FC",
      "score": {
      }
    },
    {
      "round": "Matchday 23",
      "date": "2026-02-07",
      "team1": "Juve Stabia",
      "team2": "Calcio Padova",
      "score": {
      }
    },
    {
      "round": "Matchday 23",
      "date": "2026-02-07",
      "team1": "Mantova 1911 SSD",
      "team2": "SSC Bari",
      "score": {
      }
    },
    {
      "round": "Matchday 23",
      "date": "2026-02-07",
      "team1": "Modena FC",
      "team2": "Sampdoria",
      "score": {
      }
    },
    {
      "round": "Matchday 23",
      "date": "2026-02-07",
      "team1": "AC Monza",
      "team2": "US Avellino",
      "score": {
      }
    },
    {
      "round": "Matchday 23",
      "date": "2026-02-07",
      "team1": "Palermo FC",
      "team2": "Empoli FC",
      "score": {
      }
    },
    {
      "round": "Matchday 23",
      "date": "2026-02-07",
      "team1": "Spezia Calcio",
      "team2": "Virtus Entella",
      "score": {
      }
    },
    {
      "round": "Matchday 24",
      "date": "2026-02-10",
      "team1": "US Avellino",
      "team2": "Frosinone Calcio",
      "score": {
      }
    },
    {
      "round": "Matchday 24",
      "date": "2026-02-10",
      "team1": "SSC Bari",
      "team2": "Spezia Calcio",
      "score": {
      }
    },
    {
      "round": "Matchday 24",
      "date": "2026-02-10",
      "team1": "Empoli FC",
      "team2": "Juve Stabia",
      "score": {
      }
    },
    {
      "round": "Matchday 24",
      "date": "2026-02-10",
      "team1": "Virtus Entella",
      "team2": "Cesena FC",
      "score": {
      }
    },
    {
      "round": "Matchday 24",
      "date": "2026-02-10",
      "team1": "Calcio Padova",
      "team2": "Carrarese Calcio",
      "score": {
      }
    },
    {
      "round": "Matchday 24",
      "date": "2026-02-10",
      "team1": "Delfino Pescara",
      "team2": "US Catanzaro",
      "score": {
      }
    },
    {
      "round": "Matchday 24",
      "date": "2026-02-10",
      "team1": "AC Reggiana 1919",
      "team2": "Mantova 1911 SSD",
      "score": {
      }
    },
    {
      "round": "Matchday 24",
      "date": "2026-02-10",
      "team1": "Sampdoria",
      "team2": "Palermo FC",
      "score": {
      }
    },
    {
      "round": "Matchday 24",
      "date": "2026-02-10",
      "team1": "FC Südtirol",
      "team2": "AC Monza",
      "score": {
      }
    },
    {
      "round": "Matchday 24",
      "date": "2026-02-10",
      "team1": "Venezia FC",
      "team2": "Modena FC",
      "score": {
      }
    },
    {
      "round": "Matchday 25",
      "date": "2026-02-14",
      "team1": "US Avellino",
      "team2": "Delfino Pescara",
      "score": {
      }
    },
    {
      "round": "Matchday 25",
      "date": "2026-02-14",
      "team1": "SSC Bari",
      "team2": "FC Südtirol",
      "score": {
      }
    },
    {
      "round": "Matchday 25",
      "date": "2026-02-14",
      "team1": "US Catanzaro",
      "team2": "Mantova 1911 SSD",
      "score": {
      }
    },
    {
      "round": "Matchday 25",
      "date": "2026-02-14",
      "team1": "Cesena FC",
      "team2": "Venezia FC",
      "score": {
      }
    },
    {
      "round": "Matchday 25",
      "date": "2026-02-14",
      "team1": "Empoli FC",
      "team2": "AC Reggiana 1919",
      "score": {
      }
    },
    {
      "round": "Matchday 25",
      "date": "2026-02-14",
      "team1": "Modena FC",
      "team2": "Carrarese Calcio",
      "score": {
      }
    },
    {
      "round": "Matchday 25",
      "date": "2026-02-14",
      "team1": "AC Monza",
      "team2": "Juve Stabia",
      "score": {
      }
    },
    {
      "round": "Matchday 25",
      "date": "2026-02-14",
      "team1": "Palermo FC",
      "team2": "Virtus Entella",
      "score": {
      }
    },
    {
      "round": "Matchday 25",
      "date": "2026-02-14",
      "team1": "Sampdoria",
      "team2": "Calcio Padova",
      "score": {
      }
    },
    {
      "round": "Matchday 25",
      "date": "2026-02-14",
      "team1": "Spezia Calcio",
      "team2": "Frosinone Calcio",
      "score": {
      }
    },
    {
      "round": "Matchday 26",
      "date": "2026-02-21",
      "team1": "Carrarese Calcio",
      "team2": "AC Monza",
      "score": {
      }
    },
    {
      "round": "Matchday 26",
      "date": "2026-02-21",
      "team1": "Cesena FC",
      "team2": "Spezia Calcio",
      "score": {
      }
    },
    {
      "round": "Matchday 26",
      "date": "2026-02-21",
      "team1": "Virtus Entella",
      "team2": "US Catanzaro",
      "score": {
      }
    },
    {
      "round": "Matchday 26",
      "date": "2026-02-21",
      "team1": "Frosinone Calcio",
      "team2": "Empoli FC",
      "score": {
      }
    },
    {
      "round": "Matchday 26",
      "date": "2026-02-21",
      "team1": "Juve Stabia",
      "team2": "Modena FC",
      "score": {
      }
    },
    {
      "round": "Matchday 26",
      "date": "2026-02-21",
      "team1": "Mantova 1911 SSD",
      "team2": "Sampdoria",
      "score": {
      }
    },
    {
      "round": "Matchday 26",
      "date": "2026-02-21",
      "team1": "Calcio Padova",
      "team2": "SSC Bari",
      "score": {
      }
    },
    {
      "round": "Matchday 26",
      "date": "2026-02-21",
      "team1": "Palermo FC",
      "team2": "FC Südtirol",
      "score": {
      }
    },
    {
      "round": "Matchday 26",
      "date": "2026-02-21",
      "team1": "AC Reggiana 1919",
      "team2": "US Avellino",
      "score": {
      }
    },
    {
      "round": "Matchday 26",
      "date": "2026-02-21",
      "team1": "Venezia FC",
      "team2": "Delfino Pescara",
      "score": {
      }
    },
    {
      "round": "Matchday 27",
      "date": "2026-02-28",
      "team1": "US Avellino",
      "team2": "Juve Stabia",
      "score": {
      }
    },
    {
      "round": "Matchday 27",
      "date": "2026-02-28",
      "team1": "US Catanzaro",
      "team2": "Frosinone Calcio",
      "score": {
      }
    },
    {
      "round": "Matchday 27",
      "date": "2026-02-28",
      "team1": "Empoli FC",
      "team2": "Cesena FC",
      "score": {
      }
    },
    {
      "round": "Matchday 27",
      "date": "2026-02-28",
      "team1": "Mantova 1911 SSD",
      "team2": "Carrarese Calcio",
      "score": {
      }
    },
    {
      "round": "Matchday 27",
      "date": "2026-02-28",
      "team1": "Modena FC",
      "team2": "Calcio Padova",
      "score": {
      }
    },
    {
      "round": "Matchday 27",
      "date": "2026-02-28",
      "team1": "AC Monza",
      "team2": "Virtus Entella",
      "score": {
      }
    },
    {
      "round": "Matchday 27",
      "date": "2026-02-28",
      "team1": "Delfino Pescara",
      "team2": "Palermo FC",
      "score": {
      }
    },
    {
      "round": "Matchday 27",
      "date": "2026-02-28",
      "team1": "Sampdoria",
      "team2": "SSC Bari",
      "score": {
      }
    },
    {
      "round": "Matchday 27",
      "date": "2026-02-28",
      "team1": "Spezia Calcio",
      "team2": "AC Reggiana 1919",
      "score": {
      }
    },
    {
      "round": "Matchday 27",
      "date": "2026-02-28",
      "team1": "FC Südtirol",
      "team2": "Venezia FC",
      "score": {
      }
    },
    {
      "round": "Matchday 28",
      "date": "2026-03-03",
      "team1": "SSC Bari",
      "team2": "Empoli FC",
      "score": {
      }
    },
    {
      "round": "Matchday 28",
      "date": "2026-03-03",
      "team1": "Carrarese Calcio",
      "team2": "US Catanzaro",
      "score": {
      }
    },
    {
      "round": "Matchday 28",
      "date": "2026-03-03",
      "team1": "Cesena FC",
      "team2": "AC Monza",
      "score": {
      }
    },
    {
      "round": "Matchday 28",
      "date": "2026-03-03",
      "team1": "Virtus Entella",
      "team2": "Modena FC",
      "score": {
      }
    },
    {
      "round": "Matchday 28",
      "date": "2026-03-03",
      "team1": "Frosinone Calcio",
      "team2": "Delfino Pescara",
      "score": {
      }
    },
    {
      "round": "Matchday 28",
      "date": "2026-03-03",
      "team1": "Juve Stabia",
      "team2": "Sampdoria",
      "score": {
      }
    },
    {
      "round": "Matchday 28",
      "date": "2026-03-03",
      "team1": "Calcio Padova",
      "team2": "Spezia Calcio",
      "score": {
      }
    },
    {
      "round": "Matchday 28",
      "date": "2026-03-03",
      "team1": "Palermo FC",
      "team2": "Mantova 1911 SSD",
      "score": {
      }
    },
    {
      "round": "Matchday 28",
      "date": "2026-03-03",
      "team1": "AC Reggiana 1919",
      "team2": "FC Südtirol",
      "score": {
      }
    },
    {
      "round": "Matchday 28",
      "date": "2026-03-03",
      "team1": "Venezia FC",
      "team2": "US Avellino",
      "score": {
      }
    },
    {
      "round": "Matchday 29",
      "date": "2026-03-07",
      "team1": "US Avellino",
      "team2": "Calcio Padova",
      "score": {
      }
    },
    {
      "round": "Matchday 29",
      "date": "2026-03-07",
      "team1": "Carrarese Calcio",
      "team2": "Palermo FC",
      "score": {
      }
    },
    {
      "round": "Matchday 29",
      "date": "2026-03-07",
      "team1": "US Catanzaro",
      "team2": "Empoli FC",
      "score": {
      }
    },
    {
      "round": "Matchday 29",
      "date": "2026-03-07",
      "team1": "Frosinone Calcio",
      "team2": "Sampdoria",
      "score": {
      }
    },
    {
      "round": "Matchday 29",
      "date": "2026-03-07",
      "team1": "Mantova 1911 SSD",
      "team2": "Juve Stabia",
      "score": {
      }
    },
    {
      "round": "Matchday 29",
      "date": "2026-03-07",
      "team1": "Modena FC",
      "team2": "Cesena FC",
      "score": {
      }
    },
    {
      "round": "Matchday 29",
      "date": "2026-03-07",
      "team1": "Delfino Pescara",
      "team2": "SSC Bari",
      "score": {
      }
    },
    {
      "round": "Matchday 29",
      "date": "2026-03-07",
      "team1": "Spezia Calcio",
      "team2": "AC Monza",
      "score": {
      }
    },
    {
      "round": "Matchday 29",
      "date": "2026-03-07",
      "team1": "FC Südtirol",
      "team2": "Virtus Entella",
      "score": {
      }
    },
    {
      "round": "Matchday 29",
      "date": "2026-03-07",
      "team1": "Venezia FC",
      "team2": "AC Reggiana 1919",
      "score": {
      }
    },
    {
      "round": "Matchday 30",
      "date": "2026-03-14",
      "team1": "SSC Bari",
      "team2": "AC Reggiana 1919",
      "score": {
      }
    },
    {
      "round": "Matchday 30",
      "date": "2026-03-14",
      "team1": "Cesena FC",
      "team2": "Frosinone Calcio",
      "score": {
      }
    },
    {
      "round": "Matchday 30",
      "date": "2026-03-14",
      "team1": "Empoli FC",
      "team2": "Mantova 1911 SSD",
      "score": {
      }
    },
    {
      "round": "Matchday 30",
      "date": "2026-03-14",
      "team1": "Virtus Entella",
      "team2": "US Avellino",
      "score": {
      }
    },
    {
      "round": "Matchday 30",
      "date": "2026-03-14",
      "team1": "Juve Stabia",
      "team2": "Carrarese Calcio",
      "score": {
      }
    },
    {
      "round": "Matchday 30",
      "date": "2026-03-14",
      "team1": "Modena FC",
      "team2": "Spezia Calcio",
      "score": {
      }
    },
    {
      "round": "Matchday 30",
      "date": "2026-03-14",
      "team1": "AC Monza",
      "team2": "Palermo FC",
      "score": {
      }
    },
    {
      "round": "Matchday 30",
      "date": "2026-03-14",
      "team1": "Calcio Padova",
      "team2": "US Catanzaro",
      "score": {
      }
    },
    {
      "round": "Matchday 30",
      "date": "2026-03-14",
      "team1": "Sampdoria",
      "team2": "Venezia FC",
      "score": {
      }
    },
    {
      "round": "Matchday 30",
      "date": "2026-03-14",
      "team1": "FC Südtirol",
      "team2": "Delfino Pescara",
      "score": {
      }
    },
    {
      "round": "Matchday 31",
      "date": "2026-03-17",
      "team1": "US Avellino",
      "team2": "FC Südtirol",
      "score": {
      }
    },
    {
      "round": "Matchday 31",
      "date": "2026-03-17",
      "team1": "Carrarese Calcio",
      "team2": "Sampdoria",
      "score": {
      }
    },
    {
      "round": "Matchday 31",
      "date": "2026-03-17",
      "team1": "US Catanzaro",
      "team2": "Modena FC",
      "score": {
      }
    },
    {
      "round": "Matchday 31",
      "date": "2026-03-17",
      "team1": "Frosinone Calcio",
      "team2": "SSC Bari",
      "score": {
      }
    },
    {
      "round": "Matchday 31",
      "date": "2026-03-17",
      "team1": "Mantova 1911 SSD",
      "team2": "Cesena FC",
      "score": {
      }
    },
    {
      "round": "Matchday 31",
      "date": "2026-03-17",
      "team1": "Palermo FC",
      "team2": "Juve Stabia",
      "score": {
      }
    },
    {
      "round": "Matchday 31",
      "date": "2026-03-17",
      "team1": "Delfino Pescara",
      "team2": "Virtus Entella",
      "score": {
      }
    },
    {
      "round": "Matchday 31",
      "date": "2026-03-17",
      "team1": "AC Reggiana 1919",
      "team2": "AC Monza",
      "score": {
      }
    },
    {
      "round": "Matchday 31",
      "date": "2026-03-17",
      "team1": "Spezia Calcio",
      "team2": "Empoli FC",
      "score": {
      }
    },
    {
      "round": "Matchday 31",
      "date": "2026-03-17",
      "team1": "Venezia FC",
      "team2": "Calcio Padova",
      "score": {
      }
    },
    {
      "round": "Matchday 32",
      "date": "2026-03-21",
      "team1": "SSC Bari",
      "team2": "Carrarese Calcio",
      "score": {
      }
    },
    {
      "round": "Matchday 32",
      "date": "2026-03-21",
      "team1": "Cesena FC",
      "team2": "US Catanzaro",
      "score": {
      }
    },
    {
      "round": "Matchday 32",
      "date": "2026-03-21",
      "team1": "Empoli FC",
      "team2": "Delfino Pescara",
      "score": {
      }
    },
    {
      "round": "Matchday 32",
      "date": "2026-03-21",
      "team1": "Virtus Entella",
      "team2": "AC Reggiana 1919",
      "score": {
      }
    },
    {
      "round": "Matchday 32",
      "date": "2026-03-21",
      "team1": "Juve Stabia",
      "team2": "Spezia Calcio",
      "score": {
      }
    },
    {
      "round": "Matchday 32",
      "date": "2026-03-21",
      "team1": "Modena FC",
      "team2": "Mantova 1911 SSD",
      "score": {
      }
    },
    {
      "round": "Matchday 32",
      "date": "2026-03-21",
      "team1": "AC Monza",
      "team2": "Venezia FC",
      "score": {
      }
    },
    {
      "round": "Matchday 32",
      "date": "2026-03-21",
      "team1": "Calcio Padova",
      "team2": "Palermo FC",
      "score": {
      }
    },
    {
      "round": "Matchday 32",
      "date": "2026-03-21",
      "team1": "Sampdoria",
      "team2": "US Avellino",
      "score": {
      }
    },
    {
      "round": "Matchday 32",
      "date": "2026-03-21",
      "team1": "FC Südtirol",
      "team2": "Frosinone Calcio",
      "score": {
      }
    },
    {
      "round": "Matchday 33",
      "date": "2026-04-06",
      "team1": "SSC Bari",
      "team2": "Modena FC",
      "score": {
      }
    },
    {
      "round": "Matchday 33",
      "date": "2026-04-06",
      "team1": "Carrarese Calcio",
      "team2": "Spezia Calcio",
      "score": {
      }
    },
    {
      "round": "Matchday 33",
      "date": "2026-04-06",
      "team1": "US Catanzaro",
      "team2": "AC Monza",
      "score": {
      }
    },
    {
      "round": "Matchday 33",
      "date": "2026-04-06",
      "team1": "Cesena FC",
      "team2": "FC Südtirol",
      "score": {
      }
    },
    {
      "round": "Matchday 33",
      "date": "2026-04-06",
      "team1": "Frosinone Calcio",
      "team2": "Calcio Padova",
      "score": {
      }
    },
    {
      "round": "Matchday 33",
      "date": "2026-04-06",
      "team1": "Mantova 1911 SSD",
      "team2": "Virtus Entella",
      "score": {
      }
    },
    {
      "round": "Matchday 33",
      "date": "2026-04-06",
      "team1": "Palermo FC",
      "team2": "US Avellino",
      "score": {
      }
    },
    {
      "round": "Matchday 33",
      "date": "2026-04-06",
      "team1": "AC Reggiana 1919",
      "team2": "Delfino Pescara",
      "score": {
      }
    },
    {
      "round": "Matchday 33",
      "date": "2026-04-06",
      "team1": "Sampdoria",
      "team2": "Empoli FC",
      "score": {
      }
    },
    {
      "round": "Matchday 33",
      "date": "2026-04-06",
      "team1": "Venezia FC",
      "team2": "Juve Stabia",
      "score": {
      }
    },
    {
      "round": "Matchday 34",
      "date": "2026-04-11",
      "team1": "US Avellino",
      "team2": "US Catanzaro",
      "score": {
      }
    },
    {
      "round": "Matchday 34",
      "date": "2026-04-11",
      "team1": "Virtus Entella",
      "team2": "Venezia FC",
      "score": {
      }
    },
    {
      "round": "Matchday 34",
      "date": "2026-04-11",
      "team1": "Frosinone Calcio",
      "team2": "Palermo FC",
      "score": {
      }
    },
    {
      "round": "Matchday 34",
      "date": "2026-04-11",
      "team1": "Juve Stabia",
      "team2": "Cesena FC",
      "score": {
      }
    },
    {
      "round": "Matchday 34",
      "date": "2026-04-11",
      "team1": "AC Monza",
      "team2": "SSC Bari",
      "score": {
      }
    },
    {
      "round": "Matchday 34",
      "date": "2026-04-11",
      "team1": "Calcio Padova",
      "team2": "Empoli FC",
      "score": {
      }
    },
    {
      "round": "Matchday 34",
      "date": "2026-04-11",
      "team1": "Delfino Pescara",
      "team2": "Sampdoria",
      "score": {
      }
    },
    {
      "round": "Matchday 34",
      "date": "2026-04-11",
      "team1": "AC Reggiana 1919",
      "team2": "Carrarese Calcio",
      "score": {
      }
    },
    {
      "round": "Matchday 34",
      "date": "2026-04-11",
      "team1": "Spezia Calcio",
      "team2": "Mantova 1911 SSD",
      "score": {
      }
    },
    {
      "round": "Matchday 34",
      "date": "2026-04-11",
      "team1": "FC Südtirol",
      "team2": "Modena FC",
      "score": {
      }
    },
    {
      "round": "Matchday 35",
      "date": "2026-04-18",
      "team1": "SSC Bari",
      "team2": "Venezia FC",
      "score": {
      }
    },
    {
      "round": "Matchday 35",
      "date": "2026-04-18",
      "team1": "Carrarese Calcio",
      "team2": "Delfino Pescara",
      "score": {
      }
    },
    {
      "round": "Matchday 35",
      "date": "2026-04-18",
      "team1": "Empoli FC",
      "team2": "Virtus Entella",
      "score": {
      }
    },
    {
      "round": "Matchday 35",
      "date": "2026-04-18",
      "team1": "Juve Stabia",
      "team2": "US Catanzaro",
      "score": {
      }
    },
    {
      "round": "Matchday 35",
      "date": "2026-04-18",
      "team1": "Mantova 1911 SSD",
      "team2": "US Avellino",
      "score": {
      }
    },
    {
      "round": "Matchday 35",
      "date": "2026-04-18",
      "team1": "Modena FC",
      "team2": "Frosinone Calcio",
      "score": {
      }
    },
    {
      "round": "Matchday 35",
      "date": "2026-04-18",
      "team1": "Calcio Padova",
      "team2": "AC Reggiana 1919",
      "score": {
      }
    },
    {
      "round": "Matchday 35",
      "date": "2026-04-18",
      "team1": "Palermo FC",
      "team2": "Cesena FC",
      "score": {
      }
    },
    {
      "round": "Matchday 35",
      "date": "2026-04-18",
      "team1": "Sampdoria",
      "team2": "AC Monza",
      "score": {
      }
    },
    {
      "round": "Matchday 35",
      "date": "2026-04-18",
      "team1": "Spezia Calcio",
      "team2": "FC Südtirol",
      "score": {
      }
    },
    {
      "round": "Matchday 36",
      "date": "2026-04-25",
      "team1": "US Avellino",
      "team2": "SSC Bari",
      "score": {
      }
    },
    {
      "round": "Matchday 36",
      "date": "2026-04-25",
      "team1": "US Catanzaro",
      "team2": "Spezia Calcio",
      "score": {
      }
    },
    {
      "round": "Matchday 36",
      "date": "2026-04-25",
      "team1": "Cesena FC",
      "team2": "Sampdoria",
      "score": {
      }
    },
    {
      "round": "Matchday 36",
      "date": "2026-04-25",
      "team1": "Virtus Entella",
      "team2": "Calcio Padova",
      "score": {
      }
    },
    {
      "round": "Matchday 36",
      "date": "2026-04-25",
      "team1": "Frosinone Calcio",
      "team2": "Carrarese Calcio",
      "score": {
      }
    },
    {
      "round": "Matchday 36",
      "date": "2026-04-25",
      "team1": "AC Monza",
      "team2": "Modena FC",
      "score": {
      }
    },
    {
      "round": "Matchday 36",
      "date": "2026-04-25",
      "team1": "Delfino Pescara",
      "team2": "Juve Stabia",
      "score": {
      }
    },
    {
      "round": "Matchday 36",
      "date": "2026-04-25",
      "team1": "AC Reggiana 1919",
      "team2": "Palermo FC",
      "score": {
      }
    },
    {
      "round": "Matchday 36",
      "date": "2026-04-25",
      "team1": "FC Südtirol",
      "team2": "Mantova 1911 SSD",
      "score": {
      }
    },
    {
      "round": "Matchday 36",
      "date": "2026-04-25",
      "team1": "Venezia FC",
      "team2": "Empoli FC",
      "score": {
      }
    },
    {
      "round": "Matchday 37",
      "date": "2026-05-01",
      "team1": "SSC Bari",
      "team2": "Virtus Entella",
      "score": {
      }
    },
    {
      "round": "Matchday 37",
      "date": "2026-05-01",
      "team1": "Carrarese Calcio",
      "team2": "Cesena FC",
      "score": {
      }
    },
    {
      "round": "Matchday 37",
      "date": "2026-05-01",
      "team1": "Empoli FC",
      "team2": "US Avellino",
      "score": {
      }
    },
    {
      "round": "Matchday 37",
      "date": "2026-05-01",
      "team1": "Juve Stabia",
      "team2": "Frosinone Calcio",
      "score": {
      }
    },
    {
      "round": "Matchday 37",
      "date": "2026-05-01",
      "team1": "Mantova 1911 SSD",
      "team2": "AC Monza",
      "score": {
      }
    },
    {
      "round": "Matchday 37",
      "date": "2026-05-01",
      "team1": "Modena FC",
      "team2": "AC Reggiana 1919",
      "score": {
      }
    },
    {
      "round": "Matchday 37",
      "date": "2026-05-01",
      "team1": "Calcio Padova",
      "team2": "Delfino Pescara",
      "score": {
      }
    },
    {
      "round": "Matchday 37",
      "date": "2026-05-01",
      "team1": "Palermo FC",
      "team2": "US Catanzaro",
      "score": {
      }
    },
    {
      "round": "Matchday 37",
      "date": "2026-05-01",
      "team1": "Sampdoria",
      "team2": "FC Südtirol",
      "score": {
      }
    },
    {
      "round": "Matchday 37",
      "date": "2026-05-01",
      "team1": "Spezia Calcio",
      "team2": "Venezia FC",
      "score": {
      }
    },
    {
      "round": "Matchday 38",
      "date": "2026-05-09",
      "team1": "US Avellino",
      "team2": "Modena FC",
      "score": {
      }
    },
    {
      "round": "Matchday 38",
      "date": "2026-05-09",
      "team1": "US Catanzaro",
      "team2": "SSC Bari",
      "score": {
      }
    },
    {
      "round": "Matchday 38",
      "date": "2026-05-09",
      "team1": "Cesena FC",
      "team2": "Calcio Padova",
      "score": {
      }
    },
    {
      "round": "Matchday 38",
      "date": "2026-05-09",
      "team1": "Virtus Entella",
      "team2": "Carrarese Calcio",
      "score": {
      }
    },
    {
      "round": "Matchday 38",
      "date": "2026-05-09",
      "team1": "Frosinone Calcio",
      "team2": "Mantova 1911 SSD",
      "score": {
      }
    },
    {
      "round": "Matchday 38",
      "date": "2026-05-09",
      "team1": "AC Monza",
      "team2": "Empoli FC",
      "score": {
      }
    },
    {
      "round": "Matchday 38",
      "date": "2026-05-09",
      "team1": "Delfino Pescara",
      "team2": "Spezia Calcio",
      "score": {
      }
    },
    {
      "round": "Matchday 38",
      "date": "2026-05-09",
      "team1": "AC Reggiana 1919",
      "team2": "Sampdoria",
      "score": {
      }
    },
    {
      "round": "Matchday 38",
      "date": "2026-05-09",
      "team1": "FC Südtirol",
      "team2": "Juve Stabia",
      "score": {
      }
    },
    {
      "round": "Matchday 38",
      "date": "2026-05-09",
      "team1": "Venezia FC",
      "team2": "Palermo FC",
      "score": {
      }
    }
  ]
}