{
  "name": "Bundesliga 2022/23",
  "matches": [
    {
      "round": "Matchday 1",
      "date": "2022-08-05",
      "time": "20:35",
      "team1": "Eintracht Frankfurt",
      "team2": "FC Bayern München",
      "score": {
        "ht": [
          0,
          5
        ],
        "ft": [
          1,
          6
        ]
      }
    },
    {
      "round": "Matchday 1",
      "date": "2022-08-06",
      "time": "15:30",
      "team1": "FC Augsburg",
      "team2": "SC Freiburg",
      "score": {
        "ht": [
          0,
          0
        ],
        "ft": [
          0,
          4
        ]
      }
    },
    {
      "round": "Matchday 1",
      "date": "2022-08-06",
      "time": "15:30",
      "team1": "VfL Bochum 1848",
      "team2": "1. FSV Mainz 05",
      "score": {
        "ht": [
          1,
          1
        ],
        "ft": [
          1,
          2
        ]
      }
    },
    {
      "round": "Matchday 1",
      "date": "2022-08-06",
      "time": "15:30",
      "team1": "VfL Wolfsburg",
      "team2": "SV Werder Bremen",
      "score": {
        "ht": [
          1,
          2
        ],
        "ft": [
          2,
          2
        ]
      }
    },
    {
      "round": "Matchday 1",
      "date": "2022-08-06",
      "time": "15:30",
      "team1": "Borussia Mönchengladbach",
      "team2": "TSG 1899 Hoffenheim",
      "score": {
        "ht": [
          1,
          1
        ],
        "ft": [
          3,
          1
        ]
      }
    },
    {
      "round": "Matchday 1",
      "date": "2022-08-06",
      "time": "15:30",
      "team1": "1. FC Union Berlin",
      "team2": "Hertha BSC",
      "score": {
        "ht": [
          1,
          0
        ],
        "ft": [
          3,
          1
        ]
      }
    },
    {
      "round": "Matchday 1",
      "date": "2022-08-06",
      "time": "18:30",
      "team1": "Borussia Dortmund",
      "team2": "Bayer 04 Leverkusen",
      "score": {
        "ht": [
          1,
          0
        ],
        "ft": [
          1,
          0
        ]
      }
    },
    {
      "round": "Matchday 1",
      "date": "2022-08-07",
      "time": "15:30",
      "team1": "VfB Stuttgart",
      "team2": "RB Leipzig",
      "score": {
        "ht": [
          1,
          1
        ],
        "ft": [
          1,
          1
        ]
      }
    },
    {
      "round": "Matchday 1",
      "date": "2022-08-07",
      "time": "17:30",
      "team1": "1. FC Köln",
      "team2": "FC Schalke 04",
      "score": {
        "ht": [
          0,
          0
        ],
        "ft": [
          3,
          1
        ]
      }
    },
    {
      "round": "Matchday 2",
      "date": "2022-08-12",
      "time": "20:30",
      "team1": "SC Freiburg",
      "team2": "Borussia Dortmund",
      "score": {
        "ht": [
          1,
          0
        ],
        "ft": [
          1,
          3
        ]
      }
    },
    {
      "round": "Matchday 2",
      "date": "2022-08-13",
      "time": "15:30",
      "team1": "SV Werder Bremen",
      "team2": "VfB Stuttgart",
      "score": {
        "ht": [
          1,
          1
        ],
        "ft": [
          2,
          2
        ]
      }
    },
    {
      "round": "Matchday 2",
      "date": "2022-08-13",
      "time": "15:30",
      "team1": "Hertha BSC",
      "team2": "Eintracht Frankfurt",
      "score": {
        "ht": [
          1,
          0
        ],
        "ft": [
          1,
          1
        ]
      }
    },
    {
      "round": "Matchday 2",
      "date": "2022-08-13",
      "time": "15:30",
      "team1": "TSG 1899 Hoffenheim",
      "team2": "VfL Bochum 1848",
      "score": {
        "ht": [
          2,
          2
        ],
        "ft": [
          3,
          2
        ]
      }
    },
    {
      "round": "Matchday 2",
      "date": "2022-08-13",
      "time": "15:30",
      "team1": "RB Leipzig",
      "team2": "1. FC Köln",
      "score": {
        "ht": [
          1,
          1
        ],
        "ft": [
          2,
          2
        ]
      }
    },
    {
      "round": "Matchday 2",
      "date": "2022-08-13",
      "time": "15:30",
      "team1": "Bayer 04 Leverkusen",
      "team2": "FC Augsburg",
      "score": {
        "ht": [
          1,
          1
        ],
        "ft": [
          1,
          2
        ]
      }
    },
    {
      "round": "Matchday 2",
      "date": "2022-08-13",
      "time": "18:30",
      "team1": "FC Schalke 04",
      "team2": "Borussia Mönchengladbach",
      "score": {
        "ht": [
          1,
          0
        ],
        "ft": [
          2,
          2
        ]
      }
    },
    {
      "round": "Matchday 2",
      "date": "2022-08-14",
      "time": "15:30",
      "team1": "1. FSV Mainz 05",
      "team2": "1. FC Union Berlin",
      "score": {
        "ft": [
          0,
          0
        ]
      }
    },
    {
      "round": "Matchday 2",
      "date": "2022-08-14",
      "time": "17:30",
      "team1": "FC Bayern München",
      "team2": "VfL Wolfsburg",
      "score": {
        "ht": [
          2,
          0
        ],
        "ft": [
          2,
          0
        ]
      }
    },
    {
      "round": "Matchday 3",
      "date": "2022-08-19",
      "time": "20:30",
      "team1": "Borussia Mönchengladbach",
      "team2": "Hertha BSC",
      "score": {
        "ht": [
          1,
          0
        ],
        "ft": [
          1,
          0
        ]
      }
    },
    {
      "round": "Matchday 3",
      "date": "2022-08-20",
      "time": "15:30",
      "team1": "VfB Stuttgart",
      "team2": "SC Freiburg",
      "score": {
        "ht": [
          0,
          1
        ],
        "ft": [
          0,
          1
        ]
      }
    },
    {
      "round": "Matchday 3",
      "date": "2022-08-20",
      "time": "15:30",
      "team1": "FC Augsburg",
      "team2": "1. FSV Mainz 05",
      "score": {
        "ht": [
          1,
          1
        ],
        "ft": [
          1,
          2
        ]
      }
    },
    {
      "round": "Matchday 3",
      "date": "2022-08-20",
      "time": "15:30",
      "team1": "VfL Wolfsburg",
      "team2": "FC Schalke 04",
      "score": {
        "ft": [
          0,
          0
        ]
      }
    },
    {
      "round": "Matchday 3",
      "date": "2022-08-20",
      "time": "15:30",
      "team1": "Bayer 04 Leverkusen",
      "team2": "TSG 1899 Hoffenheim",
      "score": {
        "ht": [
          0,
          2
        ],
        "ft": [
          0,
          3
        ]
      }
    },
    {
      "round": "Matchday 3",
      "date": "2022-08-20",
      "time": "15:30",
      "team1": "Borussia Dortmund",
      "team2": "SV Werder Bremen",
      "score": {
        "ht": [
          1,
          0
        ],
        "ft": [
          2,
          3
        ]
      }
    },
    {
      "round": "Matchday 3",
      "date": "2022-08-20",
      "time": "18:30",
      "team1": "1. FC Union Berlin",
      "team2": "RB Leipzig",
      "score": {
        "ht": [
          2,
          0
        ],
        "ft": [
          2,
          1
        ]
      }
    },
    {
      "round": "Matchday 3",
      "date": "2022-08-21",
      "time": "15:30",
      "team1": "Eintracht Frankfurt",
      "team2": "1. FC Köln",
      "score": {
        "ht": [
          0,
          0
        ],
        "ft": [
          1,
          1
        ]
      }
    },
    {
      "round": "Matchday 3",
      "date": "2022-08-21",
      "time": "17:30",
      "team1": "VfL Bochum 1848",
      "team2": "FC Bayern München",
      "score": {
        "ht": [
          0,
          4
        ],
        "ft": [
          0,
          7
        ]
      }
    },
    {
      "round": "Matchday 4",
      "date": "2022-08-26",
      "time": "20:30",
      "team1": "SC Freiburg",
      "team2": "VfL Bochum 1848",
      "score": {
        "ht": [
          0,
          0
        ],
        "ft": [
          1,
          0
        ]
      }
    },
    {
      "round": "Matchday 4",
      "date": "2022-08-27",
      "time": "15:30",
      "team1": "FC Schalke 04",
      "team2": "1. FC Union Berlin",
      "score": {
        "ht": [
          1,
          3
        ],
        "ft": [
          1,
          6
        ]
      }
    },
    {
      "round": "Matchday 4",
      "date": "2022-08-27",
      "time": "15:30",
      "team1": "Hertha BSC",
      "team2": "Borussia Dortmund",
      "score": {
        "ht": [
          0,
          1
        ],
        "ft": [
          0,
          1
        ]
      }
    },
    {
      "round": "Matchday 4",
      "date": "2022-08-27",
      "time": "15:30",
      "team1": "TSG 1899 Hoffenheim",
      "team2": "FC Augsburg",
      "score": {
        "ht": [
          1,
          0
        ],
        "ft": [
          1,
          0
        ]
      }
    },
    {
      "round": "Matchday 4",
      "date": "2022-08-27",
      "time": "15:30",
      "team1": "1. FSV Mainz 05",
      "team2": "Bayer 04 Leverkusen",
      "score": {
        "ht": [
          0,
          3
        ],
        "ft": [
          0,
          3
        ]
      }
    },
    {
      "round": "Matchday 4",
      "date": "2022-08-27",
      "time": "15:30",
      "team1": "RB Leipzig",
      "team2": "VfL Wolfsburg",
      "score": {
        "ht": [
          1,
          0
        ],
        "ft": [
          2,
          0
        ]
      }
    },
    {
      "round": "Matchday 4",
      "date": "2022-08-27",
      "time": "18:30",
      "team1": "FC Bayern München",
      "team2": "Borussia Mönchengladbach",
      "score": {
        "ht": [
          0,
          1
        ],
        "ft": [
          1,
          1
        ]
      }
    },
    {
      "round": "Matchday 4",
      "date": "2022-08-28",
      "time": "15:30",
      "team1": "1. FC Köln",
      "team2": "VfB Stuttgart",
      "score": {
        "ft": [
          0,
          0
        ]
      }
    },
    {
      "round": "Matchday 4",
      "date": "2022-08-28",
      "time": "17:30",
      "team1": "SV Werder Bremen",
      "team2": "Eintracht Frankfurt",
      "score": {
        "ht": [
          2,
          3
        ],
        "ft": [
          3,
          4
        ]
      }
    },
    {
      "round": "Matchday 5",
      "date": "2022-09-02",
      "time": "20:30",
      "team1": "Borussia Dortmund",
      "team2": "TSG 1899 Hoffenheim",
      "score": {
        "ht": [
          1,
          0
        ],
        "ft": [
          1,
          0
        ]
      }
    },
    {
      "round": "Matchday 5",
      "date": "2022-09-03",
      "time": "15:30",
      "team1": "VfB Stuttgart",
      "team2": "FC Schalke 04",
      "score": {
        "ht": [
          1,
          1
        ],
        "ft": [
          1,
          1
        ]
      }
    },
    {
      "round": "Matchday 5",
      "date": "2022-09-03",
      "time": "15:30",
      "team1": "VfL Bochum 1848",
      "team2": "SV Werder Bremen",
      "score": {
        "ht": [
          0,
          0
        ],
        "ft": [
          0,
          2
        ]
      }
    },
    {
      "round": "Matchday 5",
      "date": "2022-09-03",
      "time": "15:30",
      "team1": "VfL Wolfsburg",
      "team2": "1. FC Köln",
      "score": {
        "ht": [
          1,
          3
        ],
        "ft": [
          2,
          4
        ]
      }
    },
    {
      "round": "Matchday 5",
      "date": "2022-09-03",
      "time": "15:30",
      "team1": "1. FC Union Berlin",
      "team2": "FC Bayern München",
      "score": {
        "ht": [
          1,
          1
        ],
        "ft": [
          1,
          1
        ]
      }
    },
    {
      "round": "Matchday 5",
      "date": "2022-09-03",
      "time": "15:30",
      "team1": "Bayer 04 Leverkusen",
      "team2": "SC Freiburg",
      "score": {
        "ht": [
          1,
          0
        ],
        "ft": [
          2,
          3
        ]
      }
    },
    {
      "round": "Matchday 5",
      "date": "2022-09-03",
      "time": "18:30",
      "team1": "Eintracht Frankfurt",
      "team2": "RB Leipzig",
      "score": {
        "ht": [
          2,
          0
        ],
        "ft": [
          4,
          0
        ]
      }
    },
    {
      "round": "Matchday 5",
      "date": "2022-09-04",
      "time": "15:30",
      "team1": "FC Augsburg",
      "team2": "Hertha BSC",
      "score": {
        "ht": [
          0,
          0
        ],
        "ft": [
          0,
          2
        ]
      }
    },
    {
      "round": "Matchday 5",
      "date": "2022-09-04",
      "time": "17:30",
      "team1": "Borussia Mönchengladbach",
      "team2": "1. FSV Mainz 05",
      "score": {
        "ht": [
          0,
          0
        ],
        "ft": [
          0,
          1
        ]
      }
    },
    {
      "round": "Matchday 6",
      "date": "2022-09-09",
      "time": "20:30",
      "team1": "SV Werder Bremen",
      "team2": "FC Augsburg",
      "score": {
        "ht": [
          0,
          0
        ],
        "ft": [
          0,
          1
        ]
      }
    },
    {
      "round": "Matchday 6",
      "date": "2022-09-10",
      "time": "15:30",
      "team1": "Hertha BSC",
      "team2": "Bayer 04 Leverkusen",
      "score": {
        "ht": [
          0,
          0
        ],
        "ft": [
          2,
          2
        ]
      }
    },
    {
      "round": "Matchday 6",
      "date": "2022-09-10",
      "time": "15:30",
      "team1": "Eintracht Frankfurt",
      "team2": "VfL Wolfsburg",
      "score": {
        "ht": [
          0,
          0
        ],
        "ft": [
          0,
          1
        ]
      }
    },
    {
      "round": "Matchday 6",
      "date": "2022-09-10",
      "time": "15:30",
      "team1": "TSG 1899 Hoffenheim",
      "team2": "1. FSV Mainz 05",
      "score": {
        "ht": [
          0,
          0
        ],
        "ft": [
          4,
          1
        ]
      }
    },
    {
      "round": "Matchday 6",
      "date": "2022-09-10",
      "time": "15:30",
      "team1": "RB Leipzig",
      "team2": "Borussia Dortmund",
      "score": {
        "ht": [
          2,
          0
        ],
        "ft": [
          3,
          0
        ]
      }
    },
    {
      "round": "Matchday 6",
      "date": "2022-09-10",
      "time": "15:30",
      "team1": "FC Bayern München",
      "team2": "VfB Stuttgart",
      "score": {
        "ht": [
          1,
          0
        ],
        "ft": [
          2,
          2
        ]
      }
    },
    {
      "round": "Matchday 6",
      "date": "2022-09-10",
      "time": "18:30",
      "team1": "FC Schalke 04",
      "team2": "VfL Bochum 1848",
      "score": {
        "ht": [
          1,
          0
        ],
        "ft": [
          3,
          1
        ]
      }
    },
    {
      "round": "Matchday 6",
      "date": "2022-09-11",
      "time": "15:30",
      "team1": "1. FC Köln",
      "team2": "1. FC Union Berlin",
      "score": {
        "ht": [
          0,
          1
        ],
        "ft": [
          0,
          1
        ]
      }
    },
    {
      "round": "Matchday 6",
      "date": "2022-09-11",
      "time": "17:30",
      "team1": "SC Freiburg",
      "team2": "Borussia Mönchengladbach",
      "score": {
        "ft": [
          0,
          0
        ]
      }
    },
    {
      "round": "Matchday 7",
      "date": "2022-09-16",
      "time": "20:30",
      "team1": "1. FSV Mainz 05",
      "team2": "Hertha BSC",
      "score": {
        "ht": [
          0,
          1
        ],
        "ft": [
          1,
          1
        ]
      }
    },
    {
      "round": "Matchday 7",
      "date": "2022-09-17",
      "time": "15:30",
      "team1": "VfB Stuttgart",
      "team2": "Eintracht Frankfurt",
      "score": {
        "ht": [
          0,
          1
        ],
        "ft": [
          1,
          3
        ]
      }
    },
    {
      "round": "Matchday 7",
      "date": "2022-09-17",
      "time": "15:30",
      "team1": "FC Augsburg",
      "team2": "FC Bayern München",
      "score": {
        "ht": [
          0,
          0
        ],
        "ft": [
          1,
          0
        ]
      }
    },
    {
      "round": "Matchday 7",
      "date": "2022-09-17",
      "time": "15:30",
      "team1": "Bayer 04 Leverkusen",
      "team2": "SV Werder Bremen",
      "score": {
        "ht": [
          0,
          0
        ],
        "ft": [
          1,
          1
        ]
      }
    },
    {
      "round": "Matchday 7",
      "date": "2022-09-17",
      "time": "15:30",
      "team1": "Borussia Dortmund",
      "team2": "FC Schalke 04",
      "score": {
        "ht": [
          0,
          0
        ],
        "ft": [
          1,
          0
        ]
      }
    },
    {
      "round": "Matchday 7",
      "date": "2022-09-17",
      "time": "18:30",
      "team1": "Borussia Mönchengladbach",
      "team2": "RB Leipzig",
      "score": {
        "ht": [
          2,
          0
        ],
        "ft": [
          3,
          0
        ]
      }
    },
    {
      "round": "Matchday 7",
      "date": "2022-09-18",
      "time": "15:30",
      "team1": "1. FC Union Berlin",
      "team2": "VfL Wolfsburg",
      "score": {
        "ht": [
          0,
          0
        ],
        "ft": [
          2,
          0
        ]
      }
    },
    {
      "round": "Matchday 7",
      "date": "2022-09-18",
      "time": "17:30",
      "team1": "VfL Bochum 1848",
      "team2": "1. FC Köln",
      "score": {
        "ht": [
          1,
          0
        ],
        "ft": [
          1,
          1
        ]
      }
    },
    {
      "round": "Matchday 7",
      "date": "2022-09-18",
      "time": "19:30",
      "team1": "TSG 1899 Hoffenheim",
      "team2": "SC Freiburg",
      "score": {
        "ft": [
          0,
          0
        ]
      }
    },
    {
      "round": "Matchday 8",
      "date": "2022-09-30",
      "time": "20:30",
      "team1": "FC Bayern München",
      "team2": "Bayer 04 Leverkusen",
      "score": {
        "ht": [
          3,
          0
        ],
        "ft": [
          4,
          0
        ]
      }
    },
    {
      "round": "Matchday 8",
      "date": "2022-10-01",
      "time": "15:30",
      "team1": "VfL Wolfsburg",
      "team2": "VfB Stuttgart",
      "score": {
        "ht": [
          2,
          2
        ],
        "ft": [
          3,
          2
        ]
      }
    },
    {
      "round": "Matchday 8",
      "date": "2022-10-01",
      "time": "15:30",
      "team1": "Eintracht Frankfurt",
      "team2": "1. FC Union Berlin",
      "score": {
        "ht": [
          2,
          0
        ],
        "ft": [
          2,
          0
        ]
      }
    },
    {
      "round": "Matchday 8",
      "date": "2022-10-01",
      "time": "15:30",
      "team1": "1. FC Köln",
      "team2": "Borussia Dortmund",
      "score": {
        "ht": [
          0,
          1
        ],
        "ft": [
          3,
          2
        ]
      }
    },
    {
      "round": "Matchday 8",
      "date": "2022-10-01",
      "time": "15:30",
      "team1": "SC Freiburg",
      "team2": "1. FSV Mainz 05",
      "score": {
        "ht": [
          2,
          0
        ],
        "ft": [
          2,
          1
        ]
      }
    },
    {
      "round": "Matchday 8",
      "date": "2022-10-01",
      "time": "15:30",
      "team1": "RB Leipzig",
      "team2": "VfL Bochum 1848",
      "score": {
        "ht": [
          2,
          0
        ],
        "ft": [
          4,
          0
        ]
      }
    },
    {
      "round": "Matchday 8",
      "date": "2022-10-01",
      "time": "18:30",
      "team1": "SV Werder Bremen",
      "team2": "Borussia Mönchengladbach",
      "score": {
        "ht": [
          4,
          0
        ],
        "ft": [
          5,
          1
        ]
      }
    },
    {
      "round": "Matchday 8",
      "date": "2022-10-02",
      "time": "15:35",
      "team1": "Hertha BSC",
      "team2": "TSG 1899 Hoffenheim",
      "score": {
        "ht": [
          1,
          1
        ],
        "ft": [
          1,
          1
        ]
      }
    },
    {
      "round": "Matchday 8",
      "date": "2022-10-02",
      "time": "17:30",
      "team1": "FC Schalke 04",
      "team2": "FC Augsburg",
      "score": {
        "ht": [
          1,
          2
        ],
        "ft": [
          2,
          3
        ]
      }
    },
    {
      "round": "Matchday 9",
      "date": "2022-10-07",
      "time": "20:30",
      "team1": "TSG 1899 Hoffenheim",
      "team2": "SV Werder Bremen",
      "score": {
        "ht": [
          1,
          1
        ],
        "ft": [
          1,
          2
        ]
      }
    },
    {
      "round": "Matchday 9",
      "date": "2022-10-08",
      "time": "15:30",
      "team1": "FC Augsburg",
      "team2": "VfL Wolfsburg",
      "score": {
        "ht": [
          0,
          1
        ],
        "ft": [
          1,
          1
        ]
      }
    },
    {
      "round": "Matchday 9",
      "date": "2022-10-08",
      "time": "15:30",
      "team1": "VfL Bochum 1848",
      "team2": "Eintracht Frankfurt",
      "score": {
        "ht": [
          0,
          0
        ],
        "ft": [
          3,
          0
        ]
      }
    },
    {
      "round": "Matchday 9",
      "date": "2022-10-08",
      "time": "15:30",
      "team1": "1. FSV Mainz 05",
      "team2": "RB Leipzig",
      "score": {
        "ht": [
          1,
          0
        ],
        "ft": [
          1,
          1
        ]
      }
    },
    {
      "round": "Matchday 9",
      "date": "2022-10-08",
      "time": "15:30",
      "team1": "Bayer 04 Leverkusen",
      "team2": "FC Schalke 04",
      "score": {
        "ht": [
          2,
          0
        ],
        "ft": [
          4,
          0
        ]
      }
    },
    {
      "round": "Matchday 9",
      "date": "2022-10-08",
      "time": "18:30",
      "team1": "Borussia Dortmund",
      "team2": "FC Bayern München",
      "score": {
        "ht": [
          0,
          1
        ],
        "ft": [
          2,
          2
        ]
      }
    },
    {
      "round": "Matchday 9",
      "date": "2022-10-09",
      "time": "15:30",
      "team1": "Borussia Mönchengladbach",
      "team2": "1. FC Köln",
      "score": {
        "ht": [
          2,
          1
        ],
        "ft": [
          5,
          2
        ]
      }
    },
    {
      "round": "Matchday 9",
      "date": "2022-10-09",
      "time": "17:30",
      "team1": "Hertha BSC",
      "team2": "SC Freiburg",
      "score": {
        "ht": [
          1,
          1
        ],
        "ft": [
          2,
          2
        ]
      }
    },
    {
      "round": "Matchday 9",
      "date": "2022-10-09",
      "time": "19:30",
      "team1": "VfB Stuttgart",
      "team2": "1. FC Union Berlin",
      "score": {
        "ht": [
          0,
          0
        ],
        "ft": [
          0,
          1
        ]
      }
    },
    {
      "round": "Matchday 10",
      "date": "2022-10-14",
      "time": "20:30",
      "team1": "FC Schalke 04",
      "team2": "TSG 1899 Hoffenheim",
      "score": {
        "ht": [
          0,
          2
        ],
        "ft": [
          0,
          3
        ]
      }
    },
    {
      "round": "Matchday 10",
      "date": "2022-10-15",
      "time": "15:30",
      "team1": "SV Werder Bremen",
      "team2": "1. FSV Mainz 05",
      "score": {
        "ht": [
          0,
          1
        ],
        "ft": [
          0,
          2
        ]
      }
    },
    {
      "round": "Matchday 10",
      "date": "2022-10-15",
      "time": "15:30",
      "team1": "VfB Stuttgart",
      "team2": "VfL Bochum 1848",
      "score": {
        "ht": [
          2,
          1
        ],
        "ft": [
          4,
          1
        ]
      }
    },
    {
      "round": "Matchday 10",
      "date": "2022-10-15",
      "time": "15:30",
      "team1": "VfL Wolfsburg",
      "team2": "Borussia Mönchengladbach",
      "score": {
        "ht": [
          1,
          1
        ],
        "ft": [
          2,
          2
        ]
      }
    },
    {
      "round": "Matchday 10",
      "date": "2022-10-15",
      "time": "15:30",
      "team1": "Eintracht Frankfurt",
      "team2": "Bayer 04 Leverkusen",
      "score": {
        "ht": [
          1,
          0
        ],
        "ft": [
          5,
          1
        ]
      }
    },
    {
      "round": "Matchday 10",
      "date": "2022-10-15",
      "time": "18:30",
      "team1": "RB Leipzig",
      "team2": "Hertha BSC",
      "score": {
        "ht": [
          3,
          0
        ],
        "ft": [
          3,
          2
        ]
      }
    },
    {
      "round": "Matchday 10",
      "date": "2022-10-16",
      "time": "15:30",
      "team1": "1. FC Köln",
      "team2": "FC Augsburg",
      "score": {
        "ht": [
          0,
          1
        ],
        "ft": [
          3,
          2
        ]
      }
    },
    {
      "round": "Matchday 10",
      "date": "2022-10-16",
      "time": "17:30",
      "team1": "1. FC Union Berlin",
      "team2": "Borussia Dortmund",
      "score": {
        "ht": [
          2,
          0
        ],
        "ft": [
          2,
          0
        ]
      }
    },
    {
      "round": "Matchday 10",
      "date": "2022-10-16",
      "time": "19:30",
      "team1": "FC Bayern München",
      "team2": "SC Freiburg",
      "score": {
        "ht": [
          2,
          0
        ],
        "ft": [
          5,
          0
        ]
      }
    },
    {
      "round": "Matchday 11",
      "date": "2022-10-21",
      "time": "20:30",
      "team1": "1. FSV Mainz 05",
      "team2": "1. FC Köln",
      "score": {
        "ht": [
          3,
          0
        ],
        "ft": [
          5,
          0
        ]
      }
    },
    {
      "round": "Matchday 11",
      "date": "2022-10-22",
      "time": "15:30",
      "team1": "FC Augsburg",
      "team2": "RB Leipzig",
      "score": {
        "ht": [
          1,
          0
        ],
        "ft": [
          3,
          3
        ]
      }
    },
    {
      "round": "Matchday 11",
      "date": "2022-10-22",
      "time": "15:30",
      "team1": "TSG 1899 Hoffenheim",
      "team2": "FC Bayern München",
      "score": {
        "ht": [
          0,
          2
        ],
        "ft": [
          0,
          2
        ]
      }
    },
    {
      "round": "Matchday 11",
      "date": "2022-10-22",
      "time": "15:30",
      "team1": "SC Freiburg",
      "team2": "SV Werder Bremen",
      "score": {
        "ht": [
          0,
          0
        ],
        "ft": [
          2,
          0
        ]
      }
    },
    {
      "round": "Matchday 11",
      "date": "2022-10-22",
      "time": "15:30",
      "team1": "Bayer 04 Leverkusen",
      "team2": "VfL Wolfsburg",
      "score": {
        "ht": [
          1,
          1
        ],
        "ft": [
          2,
          2
        ]
      }
    },
    {
      "round": "Matchday 11",
      "date": "2022-10-22",
      "time": "15:30",
      "team1": "Borussia Dortmund",
      "team2": "VfB Stuttgart",
      "score": {
        "ht": [
          3,
          0
        ],
        "ft": [
          5,
          0
        ]
      }
    },
    {
      "round": "Matchday 11",
      "date": "2022-10-22",
      "time": "18:30",
      "team1": "Borussia Mönchengladbach",
      "team2": "Eintracht Frankfurt",
      "score": {
        "ht": [
          0,
          3
        ],
        "ft": [
          1,
          3
        ]
      }
    },
    {
      "round": "Matchday 11",
      "date": "2022-10-23",
      "time": "15:30",
      "team1": "VfL Bochum 1848",
      "team2": "1. FC Union Berlin",
      "score": {
        "ht": [
          1,
          0
        ],
        "ft": [
          2,
          1
        ]
      }
    },
    {
      "round": "Matchday 11",
      "date": "2022-10-23",
      "time": "17:30",
      "team1": "Hertha BSC",
      "team2": "FC Schalke 04",
      "score": {
        "ht": [
          0,
          0
        ],
        "ft": [
          2,
          1
        ]
      }
    },
    {
      "round": "Matchday 12",
      "date": "2022-10-28",
      "time": "20:30",
      "team1": "SV Werder Bremen",
      "team2": "Hertha BSC",
      "score": {
        "ht": [
          0,
          0
        ],
        "ft": [
          1,
          0
        ]
      }
    },
    {
      "round": "Matchday 12",
      "date": "2022-10-29",
      "time": "15:30",
      "team1": "VfB Stuttgart",
      "team2": "FC Augsburg",
      "score": {
        "ht": [
          1,
          1
        ],
        "ft": [
          2,
          1
        ]
      }
    },
    {
      "round": "Matchday 12",
      "date": "2022-10-29",
      "time": "15:30",
      "team1": "VfL Wolfsburg",
      "team2": "VfL Bochum 1848",
      "score": {
        "ht": [
          2,
          0
        ],
        "ft": [
          4,
          0
        ]
      }
    },
    {
      "round": "Matchday 12",
      "date": "2022-10-29",
      "time": "15:30",
      "team1": "RB Leipzig",
      "team2": "Bayer 04 Leverkusen",
      "score": {
        "ht": [
          1,
          0
        ],
        "ft": [
          2,
          0
        ]
      }
    },
    {
      "round": "Matchday 12",
      "date": "2022-10-29",
      "time": "15:30",
      "team1": "FC Bayern München",
      "team2": "1. FSV Mainz 05",
      "score": {
        "ht": [
          3,
          1
        ],
        "ft": [
          6,
          2
        ]
      }
    },
    {
      "round": "Matchday 12",
      "date": "2022-10-29",
      "time": "18:30",
      "team1": "Eintracht Frankfurt",
      "team2": "Borussia Dortmund",
      "score": {
        "ht": [
          1,
          1
        ],
        "ft": [
          1,
          2
        ]
      }
    },
    {
      "round": "Matchday 12",
      "date": "2022-10-30",
      "time": "15:30",
      "team1": "1. FC Union Berlin",
      "team2": "Borussia Mönchengladbach",
      "score": {
        "ht": [
          0,
          1
        ],
        "ft": [
          2,
          1
        ]
      }
    },
    {
      "round": "Matchday 12",
      "date": "2022-10-30",
      "time": "17:30",
      "team1": "FC Schalke 04",
      "team2": "SC Freiburg",
      "score": {
        "ht": [
          0,
          1
        ],
        "ft": [
          0,
          2
        ]
      }
    },
    {
      "round": "Matchday 12",
      "date": "2022-10-30",
      "time": "19:30",
      "team1": "1. FC Köln",
      "team2": "TSG 1899 Hoffenheim",
      "score": {
        "ht": [
          1,
          1
        ],
        "ft": [
          1,
          1
        ]
      }
    },
    {
      "round": "Matchday 13",
      "date": "2022-11-04",
      "time": "20:30",
      "team1": "Borussia Mönchengladbach",
      "team2": "VfB Stuttgart",
      "score": {
        "ht": [
          2,
          1
        ],
        "ft": [
          3,
          1
        ]
      }
    },
    {
      "round": "Matchday 13",
      "date": "2022-11-05",
      "time": "15:30",
      "team1": "Hertha BSC",
      "team2": "FC Bayern München",
      "score": {
        "ht": [
          2,
          3
        ],
        "ft": [
          2,
          3
        ]
      }
    },
    {
      "round": "Matchday 13",
      "date": "2022-11-05",
      "time": "15:30",
      "team1": "FC Augsburg",
      "team2": "Eintracht Frankfurt",
      "score": {
        "ht": [
          1,
          1
        ],
        "ft": [
          1,
          2
        ]
      }
    },
    {
      "round": "Matchday 13",
      "date": "2022-11-05",
      "time": "15:30",
      "team1": "TSG 1899 Hoffenheim",
      "team2": "RB Leipzig",
      "score": {
        "ht": [
          0,
          1
        ],
        "ft": [
          1,
          3
        ]
      }
    },
    {
      "round": "Matchday 13",
      "date": "2022-11-05",
      "time": "15:30",
      "team1": "1. FSV Mainz 05",
      "team2": "VfL Wolfsburg",
      "score": {
        "ht": [
          0,
          1
        ],
        "ft": [
          0,
          3
        ]
      }
    },
    {
      "round": "Matchday 13",
      "date": "2022-11-05",
      "time": "15:30",
      "team1": "Borussia Dortmund",
      "team2": "VfL Bochum 1848",
      "score": {
        "ht": [
          3,
          0
        ],
        "ft": [
          3,
          0
        ]
      }
    },
    {
      "round": "Matchday 13",
      "date": "2022-11-05",
      "time": "18:30",
      "team1": "SV Werder Bremen",
      "team2": "FC Schalke 04",
      "score": {
        "ht": [
          1,
          0
        ],
        "ft": [
          2,
          1
        ]
      }
    },
    {
      "round": "Matchday 13",
      "date": "2022-11-06",
      "time": "15:30",
      "team1": "Bayer 04 Leverkusen",
      "team2": "1. FC Union Berlin",
      "score": {
        "ht": [
          0,
          0
        ],
        "ft": [
          5,
          0
        ]
      }
    },
    {
      "round": "Matchday 13",
      "date": "2022-11-06",
      "time": "17:30",
      "team1": "SC Freiburg",
      "team2": "1. FC Köln",
      "score": {
        "ht": [
          0,
          0
        ],
        "ft": [
          2,
          0
        ]
      }
    },
    {
      "round": "Matchday 14",
      "date": "2022-11-08",
      "time": "18:30",
      "team1": "VfL Wolfsburg",
      "team2": "Borussia Dortmund",
      "score": {
        "ht": [
          1,
          0
        ],
        "ft": [
          2,
          0
        ]
      }
    },
    {
      "round": "Matchday 14",
      "date": "2022-11-08",
      "time": "20:30",
      "team1": "VfB Stuttgart",
      "team2": "Hertha BSC",
      "score": {
        "ht": [
          1,
          1
        ],
        "ft": [
          2,
          1
        ]
      }
    },
    {
      "round": "Matchday 14",
      "date": "2022-11-08",
      "time": "20:30",
      "team1": "VfL Bochum 1848",
      "team2": "Borussia Mönchengladbach",
      "score": {
        "ht": [
          2,
          0
        ],
        "ft": [
          2,
          1
        ]
      }
    },
    {
      "round": "Matchday 14",
      "date": "2022-11-08",
      "time": "20:30",
      "team1": "FC Bayern München",
      "team2": "SV Werder Bremen",
      "score": {
        "ht": [
          4,
          1
        ],
        "ft": [
          6,
          1
        ]
      }
    },
    {
      "round": "Matchday 14",
      "date": "2022-11-09",
      "time": "18:30",
      "team1": "1. FC Köln",
      "team2": "Bayer 04 Leverkusen",
      "score": {
        "ht": [
          1,
          0
        ],
        "ft": [
          1,
          2
        ]
      }
    },
    {
      "round": "Matchday 14",
      "date": "2022-11-09",
      "time": "20:30",
      "team1": "FC Schalke 04",
      "team2": "1. FSV Mainz 05",
      "score": {
        "ht": [
          1,
          0
        ],
        "ft": [
          1,
          0
        ]
      }
    },
    {
      "round": "Matchday 14",
      "date": "2022-11-09",
      "time": "20:30",
      "team1": "Eintracht Frankfurt",
      "team2": "TSG 1899 Hoffenheim",
      "score": {
        "ht": [
          3,
          1
        ],
        "ft": [
          4,
          2
        ]
      }
    },
    {
      "round": "Matchday 14",
      "date": "2022-11-09",
      "time": "20:30",
      "team1": "1. FC Union Berlin",
      "team2": "FC Augsburg",
      "score": {
        "ht": [
          2,
          2
        ],
        "ft": [
          2,
          2
        ]
      }
    },
    {
      "round": "Matchday 14",
      "date": "2022-11-09",
      "time": "20:30",
      "team1": "RB Leipzig",
      "team2": "SC Freiburg",
      "score": {
        "ht": [
          0,
          0
        ],
        "ft": [
          3,
          1
        ]
      }
    },
    {
      "round": "Matchday 15",
      "date": "2022-11-11",
      "time": "20:30",
      "team1": "Borussia Mönchengladbach",
      "team2": "Borussia Dortmund",
      "score": {
        "ht": [
          3,
          2
        ],
        "ft": [
          4,
          2
        ]
      }
    },
    {
      "round": "Matchday 15",
      "date": "2022-11-12",
      "time": "15:30",
      "team1": "SV Werder Bremen",
      "team2": "RB Leipzig",
      "score": {
        "ht": [
          0,
          1
        ],
        "ft": [
          1,
          2
        ]
      }
    },
    {
      "round": "Matchday 15",
      "date": "2022-11-12",
      "time": "15:30",
      "team1": "Hertha BSC",
      "team2": "1. FC Köln",
      "score": {
        "ht": [
          1,
          0
        ],
        "ft": [
          2,
          0
        ]
      }
    },
    {
      "round": "Matchday 15",
      "date": "2022-11-12",
      "time": "15:30",
      "team1": "FC Augsburg",
      "team2": "VfL Bochum 1848",
      "score": {
        "ht": [
          0,
          0
        ],
        "ft": [
          0,
          1
        ]
      }
    },
    {
      "round": "Matchday 15",
      "date": "2022-11-12",
      "time": "15:30",
      "team1": "TSG 1899 Hoffenheim",
      "team2": "VfL Wolfsburg",
      "score": {
        "ht": [
          1,
          1
        ],
        "ft": [
          1,
          2
        ]
      }
    },
    {
      "round": "Matchday 15",
      "date": "2022-11-12",
      "time": "15:30",
      "team1": "Bayer 04 Leverkusen",
      "team2": "VfB Stuttgart",
      "score": {
        "ht": [
          1,
          0
        ],
        "ft": [
          2,
          0
        ]
      }
    },
    {
      "round": "Matchday 15",
      "date": "2022-11-12",
      "time": "18:30",
      "team1": "FC Schalke 04",
      "team2": "FC Bayern München",
      "score": {
        "ht": [
          0,
          1
        ],
        "ft": [
          0,
          2
        ]
      }
    },
    {
      "round": "Matchday 15",
      "date": "2022-11-13",
      "time": "15:30",
      "team1": "1. FSV Mainz 05",
      "team2": "Eintracht Frankfurt",
      "score": {
        "ht": [
          1,
          0
        ],
        "ft": [
          1,
          1
        ]
      }
    },
    {
      "round": "Matchday 15",
      "date": "2022-11-13",
      "time": "17:30",
      "team1": "SC Freiburg",
      "team2": "1. FC Union Berlin",
      "score": {
        "ht": [
          4,
          0
        ],
        "ft": [
          4,
          1
        ]
      }
    },
    {
      "round": "Matchday 16",
      "date": "2023-01-20",
      "time": "20:30",
      "team1": "RB Leipzig",
      "team2": "FC Bayern München",
      "score": {
        "ht": [
          0,
          1
        ],
        "ft": [
          1,
          1
        ]
      }
    },
    {
      "round": "Matchday 16",
      "date": "2023-01-21",
      "time": "15:30",
      "team1": "VfB Stuttgart",
      "team2": "1. FSV Mainz 05",
      "score": {
        "ht": [
          1,
          1
        ],
        "ft": [
          1,
          1
        ]
      }
    },
    {
      "round": "Matchday 16",
      "date": "2023-01-21",
      "time": "15:30",
      "team1": "VfL Bochum 1848",
      "team2": "Hertha BSC",
      "score": {
        "ht": [
          2,
          0
        ],
        "ft": [
          3,
          1
        ]
      }
    },
    {
      "round": "Matchday 16",
      "date": "2023-01-21",
      "time": "15:30",
      "team1": "VfL Wolfsburg",
      "team2": "SC Freiburg",
      "score": {
        "ht": [
          3,
          0
        ],
        "ft": [
          6,
          0
        ]
      }
    },
    {
      "round": "Matchday 16",
      "date": "2023-01-21",
      "time": "15:30",
      "team1": "Eintracht Frankfurt",
      "team2": "FC Schalke 04",
      "score": {
        "ht": [
          1,
          0
        ],
        "ft": [
          3,
          0
        ]
      }
    },
    {
      "round": "Matchday 16",
      "date": "2023-01-21",
      "time": "15:30",
      "team1": "1. FC Union Berlin",
      "team2": "TSG 1899 Hoffenheim",
      "score": {
        "ht": [
          0,
          1
        ],
        "ft": [
          3,
          1
        ]
      }
    },
    {
      "round": "Matchday 16",
      "date": "2023-01-21",
      "time": "18:30",
      "team1": "1. FC Köln",
      "team2": "SV Werder Bremen",
      "score": {
        "ht": [
          5,
          1
        ],
        "ft": [
          7,
          1
        ]
      }
    },
    {
      "round": "Matchday 16",
      "date": "2023-01-22",
      "time": "15:30",
      "team1": "Borussia Dortmund",
      "team2": "FC Augsburg",
      "score": {
        "ht": [
          2,
          2
        ],
        "ft": [
          4,
          3
        ]
      }
    },
    {
      "round": "Matchday 16",
      "date": "2023-01-22",
      "time": "17:30",
      "team1": "Borussia Mönchengladbach",
      "team2": "Bayer 04 Leverkusen",
      "score": {
        "ht": [
          0,
          2
        ],
        "ft": [
          2,
          3
        ]
      }
    },
    {
      "round": "Matchday 17",
      "date": "2023-01-24",
      "time": "18:30",
      "team1": "FC Schalke 04",
      "team2": "RB Leipzig",
      "score": {
        "ht": [
          0,
          4
        ],
        "ft": [
          1,
          6
        ]
      }
    },
    {
      "round": "Matchday 17",
      "date": "2023-01-24",
      "time": "20:30",
      "team1": "Hertha BSC",
      "team2": "VfL Wolfsburg",
      "score": {
        "ht": [
          0,
          3
        ],
        "ft": [
          0,
          5
        ]
      }
    },
    {
      "round": "Matchday 17",
      "date": "2023-01-24",
      "time": "20:30",
      "team1": "TSG 1899 Hoffenheim",
      "team2": "VfB Stuttgart",
      "score": {
        "ht": [
          1,
          1
        ],
        "ft": [
          2,
          2
        ]
      }
    },
    {
      "round": "Matchday 17",
      "date": "2023-01-24",
      "time": "20:30",
      "team1": "FC Bayern München",
      "team2": "1. FC Köln",
      "score": {
        "ht": [
          0,
          1
        ],
        "ft": [
          1,
          1
        ]
      }
    },
    {
      "round": "Matchday 17",
      "date": "2023-01-25",
      "time": "18:30",
      "team1": "1. FSV Mainz 05",
      "team2": "Borussia Dortmund",
      "score": {
        "ht": [
          1,
          1
        ],
        "ft": [
          1,
          2
        ]
      }
    },
    {
      "round": "Matchday 17",
      "date": "2023-01-25",
      "time": "20:30",
      "team1": "SV Werder Bremen",
      "team2": "1. FC Union Berlin",
      "score": {
        "ht": [
          1,
          1
        ],
        "ft": [
          1,
          2
        ]
      }
    },
    {
      "round": "Matchday 17",
      "date": "2023-01-25",
      "time": "20:30",
      "team1": "FC Augsburg",
      "team2": "Borussia Mönchengladbach",
      "score": {
        "ht": [
          0,
          0
        ],
        "ft": [
          1,
          0
        ]
      }
    },
    {
      "round": "Matchday 17",
      "date": "2023-01-25",
      "time": "20:30",
      "team1": "SC Freiburg",
      "team2": "Eintracht Frankfurt",
      "score": {
        "ht": [
          0,
          1
        ],
        "ft": [
          1,
          1
        ]
      }
    },
    {
      "round": "Matchday 17",
      "date": "2023-01-25",
      "time": "20:30",
      "team1": "Bayer 04 Leverkusen",
      "team2": "VfL Bochum 1848",
      "score": {
        "ht": [
          1,
          0
        ],
        "ft": [
          2,
          0
        ]
      }
    },
    {
      "round": "Matchday 18",
      "date": "2023-01-27",
      "time": "20:30",
      "team1": "RB Leipzig",
      "team2": "VfB Stuttgart",
      "score": {
        "ht": [
          1,
          0
        ],
        "ft": [
          2,
          1
        ]
      }
    },
    {
      "round": "Matchday 18",
      "date": "2023-01-28",
      "time": "15:30",
      "team1": "SV Werder Bremen",
      "team2": "VfL Wolfsburg",
      "score": {
        "ht": [
          1,
          0
        ],
        "ft": [
          2,
          1
        ]
      }
    },
    {
      "round": "Matchday 18",
      "date": "2023-01-28",
      "time": "15:30",
      "team1": "Hertha BSC",
      "team2": "1. FC Union Berlin",
      "score": {
        "ht": [
          0,
          1
        ],
        "ft": [
          0,
          2
        ]
      }
    },
    {
      "round": "Matchday 18",
      "date": "2023-01-28",
      "time": "15:30",
      "team1": "TSG 1899 Hoffenheim",
      "team2": "Borussia Mönchengladbach",
      "score": {
        "ht": [
          0,
          2
        ],
        "ft": [
          1,
          4
        ]
      }
    },
    {
      "round": "Matchday 18",
      "date": "2023-01-28",
      "time": "15:30",
      "team1": "1. FSV Mainz 05",
      "team2": "VfL Bochum 1848",
      "score": {
        "ht": [
          3,
          0
        ],
        "ft": [
          5,
          2
        ]
      }
    },
    {
      "round": "Matchday 18",
      "date": "2023-01-28",
      "time": "15:30",
      "team1": "SC Freiburg",
      "team2": "FC Augsburg",
      "score": {
        "ht": [
          2,
          1
        ],
        "ft": [
          3,
          1
        ]
      }
    },
    {
      "round": "Matchday 18",
      "date": "2023-01-28",
      "time": "18:30",
      "team1": "FC Bayern München",
      "team2": "Eintracht Frankfurt",
      "score": {
        "ht": [
          1,
          0
        ],
        "ft": [
          1,
          1
        ]
      }
    },
    {
      "round": "Matchday 18",
      "date": "2023-01-29",
      "time": "15:30",
      "team1": "FC Schalke 04",
      "team2": "1. FC Köln",
      "score": {
        "ft": [
          0,
          0
        ]
      }
    },
    {
      "round": "Matchday 18",
      "date": "2023-01-29",
      "time": "17:30",
      "team1": "Bayer 04 Leverkusen",
      "team2": "Borussia Dortmund",
      "score": {
        "ht": [
          0,
          1
        ],
        "ft": [
          0,
          2
        ]
      }
    },
    {
      "round": "Matchday 19",
      "date": "2023-02-03",
      "time": "20:30",
      "team1": "FC Augsburg",
      "team2": "Bayer 04 Leverkusen",
      "score": {
        "ht": [
          0,
          0
        ],
        "ft": [
          1,
          0
        ]
      }
    },
    {
      "round": "Matchday 19",
      "date": "2023-02-04",
      "time": "15:30",
      "team1": "VfL Bochum 1848",
      "team2": "TSG 1899 Hoffenheim",
      "score": {
        "ht": [
          3,
          0
        ],
        "ft": [
          5,
          2
        ]
      }
    },
    {
      "round": "Matchday 19",
      "date": "2023-02-04",
      "time": "15:30",
      "team1": "Eintracht Frankfurt",
      "team2": "Hertha BSC",
      "score": {
        "ht": [
          2,
          0
        ],
        "ft": [
          3,
          0
        ]
      }
    },
    {
      "round": "Matchday 19",
      "date": "2023-02-04",
      "time": "15:30",
      "team1": "1. FC Köln",
      "team2": "RB Leipzig",
      "score": {
        "ft": [
          0,
          0
        ]
      }
    },
    {
      "round": "Matchday 19",
      "date": "2023-02-04",
      "time": "15:30",
      "team1": "1. FC Union Berlin",
      "team2": "1. FSV Mainz 05",
      "score": {
        "ht": [
          1,
          0
        ],
        "ft": [
          2,
          1
        ]
      }
    },
    {
      "round": "Matchday 19",
      "date": "2023-02-04",
      "time": "15:30",
      "team1": "Borussia Dortmund",
      "team2": "SC Freiburg",
      "score": {
        "ht": [
          1,
          1
        ],
        "ft": [
          5,
          1
        ]
      }
    },
    {
      "round": "Matchday 19",
      "date": "2023-02-04",
      "time": "18:30",
      "team1": "Borussia Mönchengladbach",
      "team2": "FC Schalke 04",
      "score": {
        "ft": [
          0,
          0
        ]
      }
    },
    {
      "round": "Matchday 19",
      "date": "2023-02-05",
      "time": "15:30",
      "team1": "VfB Stuttgart",
      "team2": "SV Werder Bremen",
      "score": {
        "ht": [
          0,
          0
        ],
        "ft": [
          0,
          2
        ]
      }
    },
    {
      "round": "Matchday 19",
      "date": "2023-02-05",
      "time": "17:30",
      "team1": "VfL Wolfsburg",
      "team2": "FC Bayern München",
      "score": {
        "ht": [
          1,
          3
        ],
        "ft": [
          2,
          4
        ]
      }
    },
    {
      "round": "Matchday 20",
      "date": "2023-02-10",
      "time": "20:30",
      "team1": "FC Schalke 04",
      "team2": "VfL Wolfsburg",
      "score": {
        "ft": [
          0,
          0
        ]
      }
    },
    {
      "round": "Matchday 20",
      "date": "2023-02-11",
      "time": "15:30",
      "team1": "SV Werder Bremen",
      "team2": "Borussia Dortmund",
      "score": {
        "ht": [
          0,
          0
        ],
        "ft": [
          0,
          2
        ]
      }
    },
    {
      "round": "Matchday 20",
      "date": "2023-02-11",
      "time": "15:30",
      "team1": "TSG 1899 Hoffenheim",
      "team2": "Bayer 04 Leverkusen",
      "score": {
        "ht": [
          0,
          1
        ],
        "ft": [
          1,
          3
        ]
      }
    },
    {
      "round": "Matchday 20",
      "date": "2023-02-11",
      "time": "15:30",
      "team1": "1. FSV Mainz 05",
      "team2": "FC Augsburg",
      "score": {
        "ht": [
          2,
          1
        ],
        "ft": [
          3,
          1
        ]
      }
    },
    {
      "round": "Matchday 20",
      "date": "2023-02-11",
      "time": "15:30",
      "team1": "SC Freiburg",
      "team2": "VfB Stuttgart",
      "score": {
        "ht": [
          0,
          1
        ],
        "ft": [
          2,
          1
        ]
      }
    },
    {
      "round": "Matchday 20",
      "date": "2023-02-11",
      "time": "15:30",
      "team1": "FC Bayern München",
      "team2": "VfL Bochum 1848",
      "score": {
        "ht": [
          1,
          0
        ],
        "ft": [
          3,
          0
        ]
      }
    },
    {
      "round": "Matchday 20",
      "date": "2023-02-11",
      "time": "18:30",
      "team1": "RB Leipzig",
      "team2": "1. FC Union Berlin",
      "score": {
        "ht": [
          1,
          0
        ],
        "ft": [
          1,
          2
        ]
      }
    },
    {
      "round": "Matchday 20",
      "date": "2023-02-12",
      "time": "15:30",
      "team1": "Hertha BSC",
      "team2": "Borussia Mönchengladbach",
      "score": {
        "ht": [
          1,
          1
        ],
        "ft": [
          4,
          1
        ]
      }
    },
    {
      "round": "Matchday 20",
      "date": "2023-02-12",
      "time": "17:30",
      "team1": "1. FC Köln",
      "team2": "Eintracht Frankfurt",
      "score": {
        "ht": [
          0,
          0
        ],
        "ft": [
          3,
          0
        ]
      }
    },
    {
      "round": "Matchday 21",
      "date": "2023-02-17",
      "time": "20:30",
      "team1": "FC Augsburg",
      "team2": "TSG 1899 Hoffenheim",
      "score": {
        "ht": [
          0,
          0
        ],
        "ft": [
          1,
          0
        ]
      }
    },
    {
      "round": "Matchday 21",
      "date": "2023-02-18",
      "time": "15:30",
      "team1": "VfL Bochum 1848",
      "team2": "SC Freiburg",
      "score": {
        "ht": [
          0,
          1
        ],
        "ft": [
          0,
          2
        ]
      }
    },
    {
      "round": "Matchday 21",
      "date": "2023-02-18",
      "time": "15:30",
      "team1": "VfL Wolfsburg",
      "team2": "RB Leipzig",
      "score": {
        "ht": [
          0,
          1
        ],
        "ft": [
          0,
          3
        ]
      }
    },
    {
      "round": "Matchday 21",
      "date": "2023-02-18",
      "time": "15:30",
      "team1": "Borussia Mönchengladbach",
      "team2": "FC Bayern München",
      "score": {
        "ht": [
          1,
          1
        ],
        "ft": [
          3,
          2
        ]
      }
    },
    {
      "round": "Matchday 21",
      "date": "2023-02-18",
      "time": "15:30",
      "team1": "VfB Stuttgart",
      "team2": "1. FC Köln",
      "score": {
        "ht": [
          1,
          0
        ],
        "ft": [
          3,
          0
        ]
      }
    },
    {
      "round": "Matchday 21",
      "date": "2023-02-18",
      "time": "18:30",
      "team1": "Eintracht Frankfurt",
      "team2": "SV Werder Bremen",
      "score": {
        "ht": [
          1,
          0
        ],
        "ft": [
          2,
          0
        ]
      }
    },
    {
      "round": "Matchday 21",
      "date": "2023-02-19",
      "time": "15:30",
      "team1": "1. FC Union Berlin",
      "team2": "FC Schalke 04",
      "score": {
        "ft": [
          0,
          0
        ]
      }
    },
    {
      "round": "Matchday 21",
      "date": "2023-02-19",
      "time": "17:30",
      "team1": "Borussia Dortmund",
      "team2": "Hertha BSC",
      "score": {
        "ht": [
          2,
          0
        ],
        "ft": [
          4,
          1
        ]
      }
    },
    {
      "round": "Matchday 21",
      "date": "2023-02-19",
      "time": "19:30",
      "team1": "Bayer 04 Leverkusen",
      "team2": "1. FSV Mainz 05",
      "score": {
        "ht": [
          1,
          2
        ],
        "ft": [
          2,
          3
        ]
      }
    },
    {
      "round": "Matchday 22",
      "date": "2023-02-24",
      "time": "20:30",
      "team1": "1. FSV Mainz 05",
      "team2": "Borussia Mönchengladbach",
      "score": {
        "ht": [
          1,
          0
        ],
        "ft": [
          4,
          0
        ]
      }
    },
    {
      "round": "Matchday 22",
      "date": "2023-02-25",
      "time": "15:30",
      "team1": "SV Werder Bremen",
      "team2": "VfL Bochum 1848",
      "score": {
        "ht": [
          2,
          0
        ],
        "ft": [
          3,
          0
        ]
      }
    },
    {
      "round": "Matchday 22",
      "date": "2023-02-25",
      "time": "15:30",
      "team1": "Hertha BSC",
      "team2": "FC Augsburg",
      "score": {
        "ht": [
          0,
          0
        ],
        "ft": [
          2,
          0
        ]
      }
    },
    {
      "round": "Matchday 22",
      "date": "2023-02-25",
      "time": "15:30",
      "team1": "TSG 1899 Hoffenheim",
      "team2": "Borussia Dortmund",
      "score": {
        "ht": [
          0,
          1
        ],
        "ft": [
          0,
          1
        ]
      }
    },
    {
      "round": "Matchday 22",
      "date": "2023-02-25",
      "time": "15:30",
      "team1": "1. FC Köln",
      "team2": "VfL Wolfsburg",
      "score": {
        "ht": [
          0,
          1
        ],
        "ft": [
          0,
          2
        ]
      }
    },
    {
      "round": "Matchday 22",
      "date": "2023-02-25",
      "time": "15:30",
      "team1": "RB Leipzig",
      "team2": "Eintracht Frankfurt",
      "score": {
        "ht": [
          2,
          0
        ],
        "ft": [
          2,
          1
        ]
      }
    },
    {
      "round": "Matchday 22",
      "date": "2023-02-25",
      "time": "18:30",
      "team1": "FC Schalke 04",
      "team2": "VfB Stuttgart",
      "score": {
        "ht": [
          2,
          0
        ],
        "ft": [
          2,
          1
        ]
      }
    },
    {
      "round": "Matchday 22",
      "date": "2023-02-26",
      "time": "15:30",
      "team1": "SC Freiburg",
      "team2": "Bayer 04 Leverkusen",
      "score": {
        "ht": [
          1,
          0
        ],
        "ft": [
          1,
          1
        ]
      }
    },
    {
      "round": "Matchday 22",
      "date": "2023-02-26",
      "time": "17:30",
      "team1": "FC Bayern München",
      "team2": "1. FC Union Berlin",
      "score": {
        "ht": [
          3,
          0
        ],
        "ft": [
          3,
          0
        ]
      }
    },
    {
      "round": "Matchday 23",
      "date": "2023-03-03",
      "time": "20:30",
      "team1": "Borussia Dortmund",
      "team2": "RB Leipzig",
      "score": {
        "ht": [
          2,
          0
        ],
        "ft": [
          2,
          1
        ]
      }
    },
    {
      "round": "Matchday 23",
      "date": "2023-03-04",
      "time": "15:30",
      "team1": "FC Augsburg",
      "team2": "SV Werder Bremen",
      "score": {
        "ht": [
          1,
          1
        ],
        "ft": [
          2,
          1
        ]
      }
    },
    {
      "round": "Matchday 23",
      "date": "2023-03-04",
      "time": "15:30",
      "team1": "VfL Bochum 1848",
      "team2": "FC Schalke 04",
      "score": {
        "ht": [
          0,
          1
        ],
        "ft": [
          0,
          2
        ]
      }
    },
    {
      "round": "Matchday 23",
      "date": "2023-03-04",
      "time": "15:30",
      "team1": "Borussia Mönchengladbach",
      "team2": "SC Freiburg",
      "score": {
        "ft": [
          0,
          0
        ]
      }
    },
    {
      "round": "Matchday 23",
      "date": "2023-03-04",
      "time": "15:30",
      "team1": "1. FSV Mainz 05",
      "team2": "TSG 1899 Hoffenheim",
      "score": {
        "ht": [
          1,
          0
        ],
        "ft": [
          1,
          0
        ]
      }
    },
    {
      "round": "Matchday 23",
      "date": "2023-03-04",
      "time": "15:30",
      "team1": "1. FC Union Berlin",
      "team2": "1. FC Köln",
      "score": {
        "ft": [
          0,
          0
        ]
      }
    },
    {
      "round": "Matchday 23",
      "date": "2023-03-04",
      "time": "18:30",
      "team1": "VfB Stuttgart",
      "team2": "FC Bayern München",
      "score": {
        "ht": [
          0,
          1
        ],
        "ft": [
          1,
          2
        ]
      }
    },
    {
      "round": "Matchday 23",
      "date": "2023-03-05",
      "time": "15:30",
      "team1": "Bayer 04 Leverkusen",
      "team2": "Hertha BSC",
      "score": {
        "ht": [
          2,
          0
        ],
        "ft": [
          4,
          1
        ]
      }
    },
    {
      "round": "Matchday 23",
      "date": "2023-03-05",
      "time": "17:30",
      "team1": "VfL Wolfsburg",
      "team2": "Eintracht Frankfurt",
      "score": {
        "ht": [
          2,
          2
        ],
        "ft": [
          2,
          2
        ]
      }
    },
    {
      "round": "Matchday 24",
      "date": "2023-03-10",
      "time": "20:30",
      "team1": "1. FC Köln",
      "team2": "VfL Bochum 1848",
      "score": {
        "ht": [
          0,
          1
        ],
        "ft": [
          0,
          2
        ]
      }
    },
    {
      "round": "Matchday 24",
      "date": "2023-03-11",
      "time": "15:30",
      "team1": "Hertha BSC",
      "team2": "1. FSV Mainz 05",
      "score": {
        "ht": [
          1,
          0
        ],
        "ft": [
          1,
          1
        ]
      }
    },
    {
      "round": "Matchday 24",
      "date": "2023-03-11",
      "time": "15:30",
      "team1": "Eintracht Frankfurt",
      "team2": "VfB Stuttgart",
      "score": {
        "ht": [
          0,
          0
        ],
        "ft": [
          1,
          1
        ]
      }
    },
    {
      "round": "Matchday 24",
      "date": "2023-03-11",
      "time": "15:30",
      "team1": "RB Leipzig",
      "team2": "Borussia Mönchengladbach",
      "score": {
        "ht": [
          0,
          0
        ],
        "ft": [
          3,
          0
        ]
      }
    },
    {
      "round": "Matchday 24",
      "date": "2023-03-11",
      "time": "15:30",
      "team1": "FC Bayern München",
      "team2": "FC Augsburg",
      "score": {
        "ht": [
          4,
          1
        ],
        "ft": [
          5,
          3
        ]
      }
    },
    {
      "round": "Matchday 24",
      "date": "2023-03-11",
      "time": "18:30",
      "team1": "FC Schalke 04",
      "team2": "Borussia Dortmund",
      "score": {
        "ht": [
          0,
          1
        ],
        "ft": [
          2,
          2
        ]
      }
    },
    {
      "round": "Matchday 24",
      "date": "2023-03-12",
      "time": "15:30",
      "team1": "SC Freiburg",
      "team2": "TSG 1899 Hoffenheim",
      "score": {
        "ht": [
          1,
          0
        ],
        "ft": [
          2,
          1
        ]
      }
    },
    {
      "round": "Matchday 24",
      "date": "2023-03-12",
      "time": "17:30",
      "team1": "SV Werder Bremen",
      "team2": "Bayer 04 Leverkusen",
      "score": {
        "ht": [
          1,
          1
        ],
        "ft": [
          2,
          3
        ]
      }
    },
    {
      "round": "Matchday 24",
      "date": "2023-03-12",
      "time": "19:30",
      "team1": "VfL Wolfsburg",
      "team2": "1. FC Union Berlin",
      "score": {
        "ht": [
          0,
          0
        ],
        "ft": [
          1,
          1
        ]
      }
    },
    {
      "round": "Matchday 25",
      "date": "2023-03-17",
      "time": "20:30",
      "team1": "Borussia Mönchengladbach",
      "team2": "SV Werder Bremen",
      "score": {
        "ht": [
          0,
          0
        ],
        "ft": [
          2,
          2
        ]
      }
    },
    {
      "round": "Matchday 25",
      "date": "2023-03-18",
      "time": "15:30",
      "team1": "VfB Stuttgart",
      "team2": "VfL Wolfsburg",
      "score": {
        "ht": [
          0,
          0
        ],
        "ft": [
          0,
          1
        ]
      }
    },
    {
      "round": "Matchday 25",
      "date": "2023-03-18",
      "time": "15:30",
      "team1": "FC Augsburg",
      "team2": "FC Schalke 04",
      "score": {
        "ht": [
          0,
          0
        ],
        "ft": [
          1,
          1
        ]
      }
    },
    {
      "round": "Matchday 25",
      "date": "2023-03-18",
      "time": "15:30",
      "team1": "VfL Bochum 1848",
      "team2": "RB Leipzig",
      "score": {
        "ht": [
          0,
          0
        ],
        "ft": [
          1,
          0
        ]
      }
    },
    {
      "round": "Matchday 25",
      "date": "2023-03-18",
      "time": "15:30",
      "team1": "TSG 1899 Hoffenheim",
      "team2": "Hertha BSC",
      "score": {
        "ht": [
          2,
          0
        ],
        "ft": [
          3,
          1
        ]
      }
    },
    {
      "round": "Matchday 25",
      "date": "2023-03-18",
      "time": "18:30",
      "team1": "Borussia Dortmund",
      "team2": "1. FC Köln",
      "score": {
        "ht": [
          4,
          1
        ],
        "ft": [
          6,
          1
        ]
      }
    },
    {
      "round": "Matchday 25",
      "date": "2023-03-19",
      "time": "15:30",
      "team1": "1. FC Union Berlin",
      "team2": "Eintracht Frankfurt",
      "score": {
        "ht": [
          0,
          0
        ],
        "ft": [
          2,
          0
        ]
      }
    },
    {
      "round": "Matchday 25",
      "date": "2023-03-19",
      "time": "17:30",
      "team1": "Bayer 04 Leverkusen",
      "team2": "FC Bayern München",
      "score": {
        "ht": [
          0,
          1
        ],
        "ft": [
          2,
          1
        ]
      }
    },
    {
      "round": "Matchday 25",
      "date": "2023-03-19",
      "time": "19:30",
      "team1": "1. FSV Mainz 05",
      "team2": "SC Freiburg",
      "score": {
        "ht": [
          0,
          0
        ],
        "ft": [
          1,
          1
        ]
      }
    },
    {
      "round": "Matchday 26",
      "date": "2023-03-31",
      "time": "20:30",
      "team1": "Eintracht Frankfurt",
      "team2": "VfL Bochum 1848",
      "score": {
        "ht": [
          1,
          1
        ],
        "ft": [
          1,
          1
        ]
      }
    },
    {
      "round": "Matchday 26",
      "date": "2023-04-01",
      "time": "15:30",
      "team1": "FC Schalke 04",
      "team2": "Bayer 04 Leverkusen",
      "score": {
        "ht": [
          0,
          0
        ],
        "ft": [
          0,
          3
        ]
      }
    },
    {
      "round": "Matchday 26",
      "date": "2023-04-01",
      "time": "15:30",
      "team1": "VfL Wolfsburg",
      "team2": "FC Augsburg",
      "score": {
        "ht": [
          0,
          2
        ],
        "ft": [
          2,
          2
        ]
      }
    },
    {
      "round": "Matchday 26",
      "date": "2023-04-01",
      "time": "15:30",
      "team1": "SC Freiburg",
      "team2": "Hertha BSC",
      "score": {
        "ht": [
          0,
          0
        ],
        "ft": [
          1,
          1
        ]
      }
    },
    {
      "round": "Matchday 26",
      "date": "2023-04-01",
      "time": "15:30",
      "team1": "1. FC Union Berlin",
      "team2": "VfB Stuttgart",
      "score": {
        "ht": [
          0,
          0
        ],
        "ft": [
          3,
          0
        ]
      }
    },
    {
      "round": "Matchday 26",
      "date": "2023-04-01",
      "time": "15:30",
      "team1": "RB Leipzig",
      "team2": "1. FSV Mainz 05",
      "score": {
        "ht": [
          0,
          1
        ],
        "ft": [
          0,
          3
        ]
      }
    },
    {
      "round": "Matchday 26",
      "date": "2023-04-01",
      "time": "18:30",
      "team1": "FC Bayern München",
      "team2": "Borussia Dortmund",
      "score": {
        "ht": [
          3,
          0
        ],
        "ft": [
          4,
          2
        ]
      }
    },
    {
      "round": "Matchday 26",
      "date": "2023-04-02",
      "time": "15:30",
      "team1": "1. FC Köln",
      "team2": "Borussia Mönchengladbach",
      "score": {
        "ft": [
          0,
          0
        ]
      }
    },
    {
      "round": "Matchday 26",
      "date": "2023-04-02",
      "time": "17:30",
      "team1": "SV Werder Bremen",
      "team2": "TSG 1899 Hoffenheim",
      "score": {
        "ht": [
          0,
          0
        ],
        "ft": [
          1,
          2
        ]
      }
    },
    {
      "round": "Matchday 27",
      "date": "2023-04-08",
      "time": "15:30",
      "team1": "FC Augsburg",
      "team2": "1. FC Köln",
      "score": {
        "ht": [
          1,
          2
        ],
        "ft": [
          1,
          3
        ]
      }
    },
    {
      "round": "Matchday 27",
      "date": "2023-04-08",
      "time": "15:30",
      "team1": "1. FSV Mainz 05",
      "team2": "SV Werder Bremen",
      "score": {
        "ht": [
          0,
          0
        ],
        "ft": [
          2,
          2
        ]
      }
    },
    {
      "round": "Matchday 27",
      "date": "2023-04-08",
      "time": "15:30",
      "team1": "SC Freiburg",
      "team2": "FC Bayern München",
      "score": {
        "ht": [
          0,
          0
        ],
        "ft": [
          0,
          1
        ]
      }
    },
    {
      "round": "Matchday 27",
      "date": "2023-04-08",
      "time": "15:30",
      "team1": "Bayer 04 Leverkusen",
      "team2": "Eintracht Frankfurt",
      "score": {
        "ht": [
          2,
          0
        ],
        "ft": [
          3,
          1
        ]
      }
    },
    {
      "round": "Matchday 27",
      "date": "2023-04-08",
      "time": "15:30",
      "team1": "Borussia Dortmund",
      "team2": "1. FC Union Berlin",
      "score": {
        "ht": [
          1,
          0
        ],
        "ft": [
          2,
          1
        ]
      }
    },
    {
      "round": "Matchday 27",
      "date": "2023-04-08",
      "time": "18:30",
      "team1": "Hertha BSC",
      "team2": "RB Leipzig",
      "score": {
        "ht": [
          0,
          1
        ],
        "ft": [
          0,
          1
        ]
      }
    },
    {
      "round": "Matchday 27",
      "date": "2023-04-09",
      "time": "15:30",
      "team1": "Borussia Mönchengladbach",
      "team2": "VfL Wolfsburg",
      "score": {
        "ht": [
          1,
          0
        ],
        "ft": [
          2,
          0
        ]
      }
    },
    {
      "round": "Matchday 27",
      "date": "2023-04-09",
      "time": "17:30",
      "team1": "VfL Bochum 1848",
      "team2": "VfB Stuttgart",
      "score": {
        "ht": [
          0,
          1
        ],
        "ft": [
          2,
          3
        ]
      }
    },
    {
      "round": "Matchday 27",
      "date": "2023-04-09",
      "time": "19:30",
      "team1": "TSG 1899 Hoffenheim",
      "team2": "FC Schalke 04",
      "score": {
        "ht": [
          1,
          0
        ],
        "ft": [
          2,
          0
        ]
      }
    },
    {
      "round": "Matchday 28",
      "date": "2023-04-14",
      "time": "20:30",
      "team1": "FC Schalke 04",
      "team2": "Hertha BSC",
      "score": {
        "ht": [
          2,
          1
        ],
        "ft": [
          5,
          2
        ]
      }
    },
    {
      "round": "Matchday 28",
      "date": "2023-04-15",
      "time": "15:30",
      "team1": "VfB Stuttgart",
      "team2": "Borussia Dortmund",
      "score": {
        "ht": [
          0,
          2
        ],
        "ft": [
          3,
          3
        ]
      }
    },
    {
      "round": "Matchday 28",
      "date": "2023-04-15",
      "time": "15:30",
      "team1": "1. FC Köln",
      "team2": "1. FSV Mainz 05",
      "score": {
        "ht": [
          0,
          1
        ],
        "ft": [
          1,
          1
        ]
      }
    },
    {
      "round": "Matchday 28",
      "date": "2023-04-15",
      "time": "15:30",
      "team1": "RB Leipzig",
      "team2": "FC Augsburg",
      "score": {
        "ht": [
          3,
          1
        ],
        "ft": [
          3,
          2
        ]
      }
    },
    {
      "round": "Matchday 28",
      "date": "2023-04-15",
      "time": "15:30",
      "team1": "FC Bayern München",
      "team2": "TSG 1899 Hoffenheim",
      "score": {
        "ht": [
          1,
          0
        ],
        "ft": [
          1,
          1
        ]
      }
    },
    {
      "round": "Matchday 28",
      "date": "2023-04-15",
      "time": "18:30",
      "team1": "Eintracht Frankfurt",
      "team2": "Borussia Mönchengladbach",
      "score": {
        "ht": [
          0,
          1
        ],
        "ft": [
          1,
          1
        ]
      }
    },
    {
      "round": "Matchday 28",
      "date": "2023-04-16",
      "time": "15:30",
      "team1": "SV Werder Bremen",
      "team2": "SC Freiburg",
      "score": {
        "ht": [
          0,
          0
        ],
        "ft": [
          1,
          2
        ]
      }
    },
    {
      "round": "Matchday 28",
      "date": "2023-04-16",
      "time": "17:30",
      "team1": "1. FC Union Berlin",
      "team2": "VfL Bochum 1848",
      "score": {
        "ht": [
          1,
          0
        ],
        "ft": [
          1,
          1
        ]
      }
    },
    {
      "round": "Matchday 28",
      "date": "2023-04-16",
      "time": "19:30",
      "team1": "VfL Wolfsburg",
      "team2": "Bayer 04 Leverkusen",
      "score": {
        "ft": [
          0,
          0
        ]
      }
    },
    {
      "round": "Matchday 29",
      "date": "2023-04-21",
      "time": "20:30",
      "team1": "FC Augsburg",
      "team2": "VfB Stuttgart",
      "score": {
        "ht": [
          1,
          0
        ],
        "ft": [
          1,
          1
        ]
      }
    },
    {
      "round": "Matchday 29",
      "date": "2023-04-22",
      "time": "15:30",
      "team1": "Hertha BSC",
      "team2": "SV Werder Bremen",
      "score": {
        "ht": [
          0,
          2
        ],
        "ft": [
          2,
          4
        ]
      }
    },
    {
      "round": "Matchday 29",
      "date": "2023-04-22",
      "time": "15:30",
      "team1": "VfL Bochum 1848",
      "team2": "VfL Wolfsburg",
      "score": {
        "ht": [
          0,
          3
        ],
        "ft": [
          1,
          5
        ]
      }
    },
    {
      "round": "Matchday 29",
      "date": "2023-04-22",
      "time": "15:30",
      "team1": "TSG 1899 Hoffenheim",
      "team2": "1. FC Köln",
      "score": {
        "ht": [
          0,
          2
        ],
        "ft": [
          1,
          3
        ]
      }
    },
    {
      "round": "Matchday 29",
      "date": "2023-04-22",
      "time": "15:30",
      "team1": "1. FSV Mainz 05",
      "team2": "FC Bayern München",
      "score": {
        "ht": [
          0,
          1
        ],
        "ft": [
          3,
          1
        ]
      }
    },
    {
      "round": "Matchday 29",
      "date": "2023-04-22",
      "time": "18:30",
      "team1": "Borussia Dortmund",
      "team2": "Eintracht Frankfurt",
      "score": {
        "ht": [
          3,
          0
        ],
        "ft": [
          4,
          0
        ]
      }
    },
    {
      "round": "Matchday 29",
      "date": "2023-04-23",
      "time": "15:30",
      "team1": "SC Freiburg",
      "team2": "FC Schalke 04",
      "score": {
        "ht": [
          2,
          0
        ],
        "ft": [
          4,
          0
        ]
      }
    },
    {
      "round": "Matchday 29",
      "date": "2023-04-23",
      "time": "17:30",
      "team1": "Bayer 04 Leverkusen",
      "team2": "RB Leipzig",
      "score": {
        "ht": [
          1,
          0
        ],
        "ft": [
          2,
          0
        ]
      }
    },
    {
      "round": "Matchday 29",
      "date": "2023-04-23",
      "time": "19:30",
      "team1": "Borussia Mönchengladbach",
      "team2": "1. FC Union Berlin",
      "score": {
        "ht": [
          0,
          0
        ],
        "ft": [
          0,
          1
        ]
      }
    },
    {
      "round": "Matchday 30",
      "date": "2023-04-28",
      "time": "20:30",
      "team1": "VfL Bochum 1848",
      "team2": "Borussia Dortmund",
      "score": {
        "ht": [
          1,
          1
        ],
        "ft": [
          1,
          1
        ]
      }
    },
    {
      "round": "Matchday 30",
      "date": "2023-04-29",
      "time": "15:30",
      "team1": "VfB Stuttgart",
      "team2": "Borussia Mönchengladbach",
      "score": {
        "ht": [
          1,
          0
        ],
        "ft": [
          2,
          1
        ]
      }
    },
    {
      "round": "Matchday 30",
      "date": "2023-04-29",
      "time": "15:30",
      "team1": "Eintracht Frankfurt",
      "team2": "FC Augsburg",
      "score": {
        "ht": [
          1,
          0
        ],
        "ft": [
          1,
          1
        ]
      }
    },
    {
      "round": "Matchday 30",
      "date": "2023-04-29",
      "time": "15:30",
      "team1": "1. FC Köln",
      "team2": "SC Freiburg",
      "score": {
        "ht": [
          0,
          0
        ],
        "ft": [
          0,
          1
        ]
      }
    },
    {
      "round": "Matchday 30",
      "date": "2023-04-29",
      "time": "15:30",
      "team1": "1. FC Union Berlin",
      "team2": "Bayer 04 Leverkusen",
      "score": {
        "ft": [
          0,
          0
        ]
      }
    },
    {
      "round": "Matchday 30",
      "date": "2023-04-29",
      "time": "15:30",
      "team1": "RB Leipzig",
      "team2": "TSG 1899 Hoffenheim",
      "score": {
        "ht": [
          1,
          0
        ],
        "ft": [
          1,
          0
        ]
      }
    },
    {
      "round": "Matchday 30",
      "date": "2023-04-29",
      "time": "18:30",
      "team1": "FC Schalke 04",
      "team2": "SV Werder Bremen",
      "score": {
        "ht": [
          0,
          1
        ],
        "ft": [
          2,
          1
        ]
      }
    },
    {
      "round": "Matchday 30",
      "date": "2023-04-30",
      "time": "15:30",
      "team1": "FC Bayern München",
      "team2": "Hertha BSC",
      "score": {
        "ht": [
          0,
          0
        ],
        "ft": [
          2,
          0
        ]
      }
    },
    {
      "round": "Matchday 30",
      "date": "2023-04-30",
      "time": "17:30",
      "team1": "VfL Wolfsburg",
      "team2": "1. FSV Mainz 05",
      "score": {
        "ht": [
          3,
          0
        ],
        "ft": [
          3,
          0
        ]
      }
    },
    {
      "round": "Matchday 31",
      "date": "2023-05-05",
      "time": "20:30",
      "team1": "1. FSV Mainz 05",
      "team2": "FC Schalke 04",
      "score": {
        "ht": [
          0,
          1
        ],
        "ft": [
          2,
          3
        ]
      }
    },
    {
      "round": "Matchday 31",
      "date": "2023-05-05",
      "time": "20:30",
      "team1": "Bayer 04 Leverkusen",
      "team2": "1. FC Köln",
      "score": {
        "ht": [
          1,
          2
        ],
        "ft": [
          1,
          2
        ]
      }
    },
    {
      "round": "Matchday 31",
      "date": "2023-05-06",
      "time": "15:30",
      "team1": "Hertha BSC",
      "team2": "VfB Stuttgart",
      "score": {
        "ht": [
          2,
          1
        ],
        "ft": [
          2,
          1
        ]
      }
    },
    {
      "round": "Matchday 31",
      "date": "2023-05-06",
      "time": "15:30",
      "team1": "FC Augsburg",
      "team2": "1. FC Union Berlin",
      "score": {
        "ht": [
          0,
          0
        ],
        "ft": [
          1,
          0
        ]
      }
    },
    {
      "round": "Matchday 31",
      "date": "2023-05-06",
      "time": "15:30",
      "team1": "Borussia Mönchengladbach",
      "team2": "VfL Bochum 1848",
      "score": {
        "ht": [
          1,
          0
        ],
        "ft": [
          2,
          0
        ]
      }
    },
    {
      "round": "Matchday 31",
      "date": "2023-05-06",
      "time": "15:30",
      "team1": "TSG 1899 Hoffenheim",
      "team2": "Eintracht Frankfurt",
      "score": {
        "ht": [
          3,
          0
        ],
        "ft": [
          3,
          1
        ]
      }
    },
    {
      "round": "Matchday 31",
      "date": "2023-05-06",
      "time": "15:30",
      "team1": "SC Freiburg",
      "team2": "RB Leipzig",
      "score": {
        "ht": [
          0,
          0
        ],
        "ft": [
          0,
          1
        ]
      }
    },
    {
      "round": "Matchday 31",
      "date": "2023-05-06",
      "time": "18:30",
      "team1": "SV Werder Bremen",
      "team2": "FC Bayern München",
      "score": {
        "ht": [
          0,
          0
        ],
        "ft": [
          1,
          2
        ]
      }
    },
    {
      "round": "Matchday 31",
      "date": "2023-05-07",
      "time": "17:30",
      "team1": "Borussia Dortmund",
      "team2": "VfL Wolfsburg",
      "score": {
        "ht": [
          3,
          0
        ],
        "ft": [
          6,
          0
        ]
      }
    },
    {
      "round": "Matchday 32",
      "date": "2023-05-12",
      "time": "20:30",
      "team1": "1. FC Köln",
      "team2": "Hertha BSC",
      "score": {
        "ht": [
          3,
          2
        ],
        "ft": [
          5,
          2
        ]
      }
    },
    {
      "round": "Matchday 32",
      "date": "2023-05-13",
      "time": "15:30",
      "team1": "VfL Bochum 1848",
      "team2": "FC Augsburg",
      "score": {
        "ht": [
          1,
          1
        ],
        "ft": [
          3,
          2
        ]
      }
    },
    {
      "round": "Matchday 32",
      "date": "2023-05-13",
      "time": "15:30",
      "team1": "VfL Wolfsburg",
      "team2": "TSG 1899 Hoffenheim",
      "score": {
        "ht": [
          1,
          0
        ],
        "ft": [
          2,
          1
        ]
      }
    },
    {
      "round": "Matchday 32",
      "date": "2023-05-13",
      "time": "15:30",
      "team1": "Eintracht Frankfurt",
      "team2": "1. FSV Mainz 05",
      "score": {
        "ht": [
          2,
          0
        ],
        "ft": [
          3,
          0
        ]
      }
    },
    {
      "round": "Matchday 32",
      "date": "2023-05-13",
      "time": "15:30",
      "team1": "1. FC Union Berlin",
      "team2": "SC Freiburg",
      "score": {
        "ht": [
          3,
          0
        ],
        "ft": [
          4,
          2
        ]
      }
    },
    {
      "round": "Matchday 32",
      "date": "2023-05-13",
      "time": "15:30",
      "team1": "FC Bayern München",
      "team2": "FC Schalke 04",
      "score": {
        "ht": [
          2,
          0
        ],
        "ft": [
          6,
          0
        ]
      }
    },
    {
      "round": "Matchday 32",
      "date": "2023-05-13",
      "time": "18:30",
      "team1": "Borussia Dortmund",
      "team2": "Borussia Mönchengladbach",
      "score": {
        "ht": [
          4,
          0
        ],
        "ft": [
          5,
          2
        ]
      }
    },
    {
      "round": "Matchday 32",
      "date": "2023-05-14",
      "time": "15:30",
      "team1": "VfB Stuttgart",
      "team2": "Bayer 04 Leverkusen",
      "score": {
        "ht": [
          0,
          0
        ],
        "ft": [
          1,
          1
        ]
      }
    },
    {
      "round": "Matchday 32",
      "date": "2023-05-14",
      "time": "17:30",
      "team1": "RB Leipzig",
      "team2": "SV Werder Bremen",
      "score": {
        "ht": [
          0,
          0
        ],
        "ft": [
          2,
          1
        ]
      }
    },
    {
      "round": "Matchday 33",
      "date": "2023-05-19",
      "time": "20:30",
      "team1": "SC Freiburg",
      "team2": "VfL Wolfsburg",
      "score": {
        "ht": [
          0,
          0
        ],
        "ft": [
          2,
          0
        ]
      }
    },
    {
      "round": "Matchday 33",
      "date": "2023-05-20",
      "time": "15:30",
      "team1": "SV Werder Bremen",
      "team2": "1. FC Köln",
      "score": {
        "ht": [
          0,
          1
        ],
        "ft": [
          1,
          1
        ]
      }
    },
    {
      "round": "Matchday 33",
      "date": "2023-05-20",
      "time": "15:30",
      "team1": "FC Schalke 04",
      "team2": "Eintracht Frankfurt",
      "score": {
        "ht": [
          1,
          1
        ],
        "ft": [
          2,
          2
        ]
      }
    },
    {
      "round": "Matchday 33",
      "date": "2023-05-20",
      "time": "15:30",
      "team1": "Hertha BSC",
      "team2": "VfL Bochum 1848",
      "score": {
        "ht": [
          0,
          0
        ],
        "ft": [
          1,
          1
        ]
      }
    },
    {
      "round": "Matchday 33",
      "date": "2023-05-20",
      "time": "15:30",
      "team1": "TSG 1899 Hoffenheim",
      "team2": "1. FC Union Berlin",
      "score": {
        "ht": [
          2,
          1
        ],
        "ft": [
          4,
          2
        ]
      }
    },
    {
      "round": "Matchday 33",
      "date": "2023-05-20",
      "time": "18:30",
      "team1": "FC Bayern München",
      "team2": "RB Leipzig",
      "score": {
        "ht": [
          1,
          0
        ],
        "ft": [
          1,
          3
        ]
      }
    },
    {
      "round": "Matchday 33",
      "date": "2023-05-21",
      "time": "15:30",
      "team1": "1. FSV Mainz 05",
      "team2": "VfB Stuttgart",
      "score": {
        "ht": [
          1,
          1
        ],
        "ft": [
          1,
          4
        ]
      }
    },
    {
      "round": "Matchday 33",
      "date": "2023-05-21",
      "time": "17:30",
      "team1": "FC Augsburg",
      "team2": "Borussia Dortmund",
      "score": {
        "ht": [
          0,
          0
        ],
        "ft": [
          0,
          3
        ]
      }
    },
    {
      "round": "Matchday 33",
      "date": "2023-05-21",
      "time": "19:30",
      "team1": "Bayer 04 Leverkusen",
      "team2": "Borussia Mönchengladbach",
      "score": {
        "ht": [
          2,
          0
        ],
        "ft": [
          2,
          2
        ]
      }
    },
    {
      "round": "Matchday 34",
      "date": "2023-05-27",
      "time": "15:30",
      "team1": "VfB Stuttgart",
      "team2": "TSG 1899 Hoffenheim",
      "score": {
        "ht": [
          0,
          0
        ],
        "ft": [
          1,
          1
        ]
      }
    },
    {
      "round": "Matchday 34",
      "date": "2023-05-27",
      "time": "15:30",
      "team1": "VfL Bochum 1848",
      "team2": "Bayer 04 Leverkusen",
      "score": {
        "ht": [
          2,
          0
        ],
        "ft": [
          3,
          0
        ]
      }
    },
    {
      "round": "Matchday 34",
      "date": "2023-05-27",
      "time": "15:30",
      "team1": "VfL Wolfsburg",
      "team2": "Hertha BSC",
      "score": {
        "ht": [
          1,
          0
        ],
        "ft": [
          1,
          2
        ]
      }
    },
    {
      "round": "Matchday 34",
      "date": "2023-05-27",
      "time": "15:30",
      "team1": "Eintracht Frankfurt",
      "team2": "SC Freiburg",
      "score": {
        "ht": [
          0,
          1
        ],
        "ft": [
          2,
          1
        ]
      }
    },
    {
      "round": "Matchday 34",
      "date": "2023-05-27",
      "time": "15:30",
      "team1": "Borussia Mönchengladbach",
      "team2": "FC Augsburg",
      "score": {
        "ht": [
          2,
          0
        ],
        "ft": [
          2,
          0
        ]
      }
    },
    {
      "round": "Matchday 34",
      "date": "2023-05-27",
      "time": "15:30",
      "team1": "1. FC Köln",
      "team2": "FC Bayern München",
      "score": {
        "ht": [
          0,
          1
        ],
        "ft": [
          1,
          2
        ]
      }
    },
    {
      "round": "Matchday 34",
      "date": "2023-05-27",
      "time": "15:30",
      "team1": "1. FC Union Berlin",
      "team2": "SV Werder Bremen",
      "score": {
        "ht": [
          0,
          0
        ],
        "ft": [
          1,
          0
        ]
      }
    },
    {
      "round": "Matchday 34",
      "date": "2023-05-27",
      "time": "15:30",
      "team1": "RB Leipzig",
      "team2": "FC Schalke 04",
      "score": {
        "ht": [
          2,
          1
        ],
        "ft": [
          4,
          2
        ]
      }
    },
    {
      "round": "Matchday 34",
      "date": "2023-05-27",
      "time": "15:30",
      "team1": "Borussia Dortmund",
      "team2": "1. FSV Mainz 05",
      "score": {
        "ht": [
          0,
          2
        ],
        "ft": [
          2,
          2
        ]
      }
    }
  ]
}